Workbook
Name cat_models: 'Catalogues'!$A$6:$A$15
Name cat_quants: 'Catalogues'!$A$20:$A$22
Name cat_gpus: 'Catalogues'!$A$26:$A$33
Name cat_plans: 'Catalogues'!$A$38:$A$47
Name cat_frontier: 'Catalogues'!$A$52:$A$55
Name cat_profiles: 'Catalogues'!$A$60:$A$62
Name tbl_models: 'Catalogues'!$A$6:$D$15
Name tbl_quants: 'Catalogues'!$A$20:$C$22
Name tbl_gpus: 'Catalogues'!$A$26:$G$33
Name tbl_plans: 'Catalogues'!$A$38:$D$47
Name tbl_frontier: 'Catalogues'!$A$52:$E$55
Name tbl_profiles: 'Catalogues'!$A$60:$G$62
Name sel_model: 'Inputs'!$B$11
Name sel_quant: 'Inputs'!$B$12
Name sel_gpu: 'Inputs'!$B$13
Name sel_plan: 'Inputs'!$B$14
Name sel_profile: 'Inputs'!$B$15
Name devs: 'Inputs'!$B$19
Name workdays: 'Inputs'!$B$20
Name inTok: 'Inputs'!$B$21
Name outTok: 'Inputs'!$B$22
Name cacheShare: 'Inputs'!$B$23
Name codeHrs: 'Inputs'!$B$24
Name acceptFrontier: 'Inputs'!$B$28
Name acceptOpen: 'Inputs'!$B$29
Name repairFrontier: 'Inputs'!$B$30
Name repairOpen: 'Inputs'!$B$31
Name hardFrontier: 'Inputs'!$B$32
Name hardOpen: 'Inputs'!$B$33
Name tasksDay: 'Inputs'!$B$34
Name minPerAttempt: 'Inputs'!$B$35
Name maxRetries: 'Inputs'!$B$36
Name minPerHumanTask: 'Inputs'!$B$37
Name countFallback: 'Inputs'!$B$38
Name ctxK: 'Inputs'!$B$42
Name batch: 'Inputs'!$B$43
Name bwEff: 'Inputs'!$B$44
Name streamCap: 'Inputs'!$B$45
Name ckpts: 'Inputs'!$B$46
Name sessConc: 'Inputs'!$B$47
Name activeHrs: 'Inputs'!$B$48
Name peak: 'Inputs'!$B$49
Name nodeSize: 'Inputs'!$B$50
Name multiNodeLoss: 'Inputs'!$B$51
Name lapBw: 'Inputs'!$B$52
Name lapRam: 'Inputs'!$B$53
Name gpuVram: 'Inputs'!$B$57
Name gpuBw: 'Inputs'!$B$58
Name gpuTf: 'Inputs'!$B$59
Name gpuBuy: 'Inputs'!$B$60
Name gpuRent: 'Inputs'!$B$61
Name gpuW: 'Inputs'!$B$62
Name hostCost: 'Inputs'!$B$63
Name rentUtil: 'Inputs'!$B$64
Name pue: 'Inputs'!$B$68
Name kwhDc: 'Inputs'!$B$69
Name coloKw: 'Inputs'!$B$70
Name storGb: 'Inputs'!$B$71
Name lapUplift: 'Inputs'!$B$72
Name lapWatts: 'Inputs'!$B$73

Sheet Answer
A1: The answer
A2: Everything here is a formula over Inputs. Change a blue cell there and this page moves.
B4: THE RECOMMENDATION
B5: =IF(AND(devs>0,devs<=soloAt),IF(devs=1,"You are one developer. Buy a plan.","A team this small should buy plans."),IF(INDEX(r_id,MATCH(1,r_rank,0))="serverless","Rent the open weights. Do not run them.",IF(INDEX(r_id,MATCH(1,r_rank,0))="hybrid","Run the cheap model first. Escalate what it cannot finish.",IF(OR(INDEX(r_id,MATCH(1,r_rank,0))="laptop",INDEX(r_id,MATCH(1,r_rank,0))="buy",INDEX(r_id,MATCH(1,r_rank,0))="rent"),"Run it on your own hardware.","Rent the model. Do not buy the hardware."))))
B7: =IF(AND(devs>0,devs<=soloAt),"The cheapest flat plan that keeps up with a live session is "&planFitName&" at "&TEXT(planFitCost,"$#,##0")&" a developer a month, "&TEXT(planFitTeam,"$#,##0")&" for "&TEXT(devs,"#,##0")&". If your use is bursty a metered key is cheaper still: the open weights on a serverless provider come to "&TEXT(Workings!$H$113,"$#,##0")&" a month at this volume. Nothing here needs a platform team, a rack or a purchase order.",IF(INDEX(r_id,MATCH(1,r_rank,0))="serverless","Someone else already owns a warm fleet of these weights and sells them by the token. At this size that beats both your own accelerators and the frontier rate card, and it carries no capital, no rota and no lead time.",IF(INDEX(r_id,MATCH(1,r_rank,0))="hybrid","Two independent attempts finish more work than either approach alone: only "&TEXT(unres_h,"0%")&" of accepted tasks still need a person, against "&TEXT(unres_f,"0%")&" on the frontier model by itself.",IF(OR(INDEX(r_id,MATCH(1,r_rank,0))="laptop",INDEX(r_id,MATCH(1,r_rank,0))="buy",INDEX(r_id,MATCH(1,r_rank,0))="rent"),"At this size the fleet is cheaper than metered tokens even after the extra attempts the weaker model needs are counted. That advantage is narrow and it depends on quality holding up.","At this team size, owning accelerators costs more than renting tokens, before the weaker output of the open model is even counted."))))
B11: Cheapest route | D11: Bill over the horizon | F11: Priciest route | H11: Spread, full term | J11: Quality budget
B12: =INDEX(r_name,MATCH(1,r_rank,0)) | D12: =INDEX(Workings!$K$110:$K$119,MATCH(1,r_rank,0)) | F12: =INDEX(r_name,MATCH(10,r_rank,0)) | H12: =(INDEX(Workings!$H$110:$H$119,MATCH(10,r_rank,0))-INDEX(Workings!$H$110:$H$119,MATCH(1,r_rank,0)))*horizon | J12: =qualityPct
B13: ="at "&TEXT(INDEX(Workings!$H$110:$H$119,MATCH(1,r_rank,0)),"$#,##0")&" a month" | D13: ="for "&TEXT(devs,"#,##0")&" developer"&IF(devs=1,"","s") | F13: ="at "&TEXT(INDEX(Workings!$H$110:$H$119,MATCH(10,r_rank,0)),"$#,##0")&" a month" | H13: ="saved by picking first over last" | J13: ="developer time the self-hosted saving buys; your acceptance gap costs "&TEXT(dragPct,"0.0%")
A15: EVERY ROUTE, CHEAPEST FIRST
A16: # | B16: Route | C16: Monthly | D16: Up front | E16: Full term | F16: Per dev / mo | G16: AI $ / task | H16: Unfinished | I16: Sustained tok/s | J16: Headroom
A17: 1 | B17: =INDEX(Workings!$A$110:$A$119,MATCH(1,r_rank,0)) | C17: =INDEX(Workings!$H$110:$H$119,MATCH(1,r_rank,0)) | D17: =INDEX(Workings!$I$110:$I$119,MATCH(1,r_rank,0)) | E17: =INDEX(Workings!$K$110:$K$119,MATCH(1,r_rank,0)) | F17: =INDEX(Workings!$N$110:$N$119,MATCH(1,r_rank,0)) | G17: =INDEX(Workings!$O$110:$O$119,MATCH(1,r_rank,0)) | H17: =INDEX(Workings!$P$110:$P$119,MATCH(1,r_rank,0)) | I17: =INDEX(Workings!$Q$110:$Q$119,MATCH(1,r_rank,0)) | J17: =INDEX(Workings!$V$110:$V$119,MATCH(1,r_rank,0))
A18: 2 | B18: =INDEX(Workings!$A$110:$A$119,MATCH(2,r_rank,0)) | C18: =INDEX(Workings!$H$110:$H$119,MATCH(2,r_rank,0)) | D18: =INDEX(Workings!$I$110:$I$119,MATCH(2,r_rank,0)) | E18: =INDEX(Workings!$K$110:$K$119,MATCH(2,r_rank,0)) | F18: =INDEX(Workings!$N$110:$N$119,MATCH(2,r_rank,0)) | G18: =INDEX(Workings!$O$110:$O$119,MATCH(2,r_rank,0)) | H18: =INDEX(Workings!$P$110:$P$119,MATCH(2,r_rank,0)) | I18: =INDEX(Workings!$Q$110:$Q$119,MATCH(2,r_rank,0)) | J18: =INDEX(Workings!$V$110:$V$119,MATCH(2,r_rank,0))
A19: 3 | B19: =INDEX(Workings!$A$110:$A$119,MATCH(3,r_rank,0)) | C19: =INDEX(Workings!$H$110:$H$119,MATCH(3,r_rank,0)) | D19: =INDEX(Workings!$I$110:$I$119,MATCH(3,r_rank,0)) | E19: =INDEX(Workings!$K$110:$K$119,MATCH(3,r_rank,0)) | F19: =INDEX(Workings!$N$110:$N$119,MATCH(3,r_rank,0)) | G19: =INDEX(Workings!$O$110:$O$119,MATCH(3,r_rank,0)) | H19: =INDEX(Workings!$P$110:$P$119,MATCH(3,r_rank,0)) | I19: =INDEX(Workings!$Q$110:$Q$119,MATCH(3,r_rank,0)) | J19: =INDEX(Workings!$V$110:$V$119,MATCH(3,r_rank,0))
A20: 4 | B20: =INDEX(Workings!$A$110:$A$119,MATCH(4,r_rank,0)) | C20: =INDEX(Workings!$H$110:$H$119,MATCH(4,r_rank,0)) | D20: =INDEX(Workings!$I$110:$I$119,MATCH(4,r_rank,0)) | E20: =INDEX(Workings!$K$110:$K$119,MATCH(4,r_rank,0)) | F20: =INDEX(Workings!$N$110:$N$119,MATCH(4,r_rank,0)) | G20: =INDEX(Workings!$O$110:$O$119,MATCH(4,r_rank,0)) | H20: =INDEX(Workings!$P$110:$P$119,MATCH(4,r_rank,0)) | I20: =INDEX(Workings!$Q$110:$Q$119,MATCH(4,r_rank,0)) | J20: =INDEX(Workings!$V$110:$V$119,MATCH(4,r_rank,0))
A21: 5 | B21: =INDEX(Workings!$A$110:$A$119,MATCH(5,r_rank,0)) | C21: =INDEX(Workings!$H$110:$H$119,MATCH(5,r_rank,0)) | D21: =INDEX(Workings!$I$110:$I$119,MATCH(5,r_rank,0)) | E21: =INDEX(Workings!$K$110:$K$119,MATCH(5,r_rank,0)) | F21: =INDEX(Workings!$N$110:$N$119,MATCH(5,r_rank,0)) | G21: =INDEX(Workings!$O$110:$O$119,MATCH(5,r_rank,0)) | H21: =INDEX(Workings!$P$110:$P$119,MATCH(5,r_rank,0)) | I21: =INDEX(Workings!$Q$110:$Q$119,MATCH(5,r_rank,0)) | J21: =INDEX(Workings!$V$110:$V$119,MATCH(5,r_rank,0))
A22: 6 | B22: =INDEX(Workings!$A$110:$A$119,MATCH(6,r_rank,0)) | C22: =INDEX(Workings!$H$110:$H$119,MATCH(6,r_rank,0)) | D22: =INDEX(Workings!$I$110:$I$119,MATCH(6,r_rank,0)) | E22: =INDEX(Workings!$K$110:$K$119,MATCH(6,r_rank,0)) | F22: =INDEX(Workings!$N$110:$N$119,MATCH(6,r_rank,0)) | G22: =INDEX(Workings!$O$110:$O$119,MATCH(6,r_rank,0)) | H22: =INDEX(Workings!$P$110:$P$119,MATCH(6,r_rank,0)) | I22: =INDEX(Workings!$Q$110:$Q$119,MATCH(6,r_rank,0)) | J22: =INDEX(Workings!$V$110:$V$119,MATCH(6,r_rank,0))
A23: 7 | B23: =INDEX(Workings!$A$110:$A$119,MATCH(7,r_rank,0)) | C23: =INDEX(Workings!$H$110:$H$119,MATCH(7,r_rank,0)) | D23: =INDEX(Workings!$I$110:$I$119,MATCH(7,r_rank,0)) | E23: =INDEX(Workings!$K$110:$K$119,MATCH(7,r_rank,0)) | F23: =INDEX(Workings!$N$110:$N$119,MATCH(7,r_rank,0)) | G23: =INDEX(Workings!$O$110:$O$119,MATCH(7,r_rank,0)) | H23: =INDEX(Workings!$P$110:$P$119,MATCH(7,r_rank,0)) | I23: =INDEX(Workings!$Q$110:$Q$119,MATCH(7,r_rank,0)) | J23: =INDEX(Workings!$V$110:$V$119,MATCH(7,r_rank,0))
A24: 8 | B24: =INDEX(Workings!$A$110:$A$119,MATCH(8,r_rank,0)) | C24: =INDEX(Workings!$H$110:$H$119,MATCH(8,r_rank,0)) | D24: =INDEX(Workings!$I$110:$I$119,MATCH(8,r_rank,0)) | E24: =INDEX(Workings!$K$110:$K$119,MATCH(8,r_rank,0)) | F24: =INDEX(Workings!$N$110:$N$119,MATCH(8,r_rank,0)) | G24: =INDEX(Workings!$O$110:$O$119,MATCH(8,r_rank,0)) | H24: =INDEX(Workings!$P$110:$P$119,MATCH(8,r_rank,0)) | I24: =INDEX(Workings!$Q$110:$Q$119,MATCH(8,r_rank,0)) | J24: =INDEX(Workings!$V$110:$V$119,MATCH(8,r_rank,0))
A25: 9 | B25: =INDEX(Workings!$A$110:$A$119,MATCH(9,r_rank,0)) | C25: =INDEX(Workings!$H$110:$H$119,MATCH(9,r_rank,0)) | D25: =INDEX(Workings!$I$110:$I$119,MATCH(9,r_rank,0)) | E25: =INDEX(Workings!$K$110:$K$119,MATCH(9,r_rank,0)) | F25: =INDEX(Workings!$N$110:$N$119,MATCH(9,r_rank,0)) | G25: =INDEX(Workings!$O$110:$O$119,MATCH(9,r_rank,0)) | H25: =INDEX(Workings!$P$110:$P$119,MATCH(9,r_rank,0)) | I25: =INDEX(Workings!$Q$110:$Q$119,MATCH(9,r_rank,0)) | J25: =INDEX(Workings!$V$110:$V$119,MATCH(9,r_rank,0))
A26: 10 | B26: =INDEX(Workings!$A$110:$A$119,MATCH(10,r_rank,0)) | C26: =INDEX(Workings!$H$110:$H$119,MATCH(10,r_rank,0)) | D26: =INDEX(Workings!$I$110:$I$119,MATCH(10,r_rank,0)) | E26: =INDEX(Workings!$K$110:$K$119,MATCH(10,r_rank,0)) | F26: =INDEX(Workings!$N$110:$N$119,MATCH(10,r_rank,0)) | G26: =INDEX(Workings!$O$110:$O$119,MATCH(10,r_rank,0)) | H26: =INDEX(Workings!$P$110:$P$119,MATCH(10,r_rank,0)) | I26: =INDEX(Workings!$Q$110:$Q$119,MATCH(10,r_rank,0)) | J26: =INDEX(Workings!$V$110:$V$119,MATCH(10,r_rank,0))
B27: Headroom below 1.0x means the route throttles and your developers queue. Laptops and per-seat plans scale one unit per developer, so their headroom is one unit against one session, not a shared pool.
A29: WHAT WOULD CHANGE THIS ANSWER
B30: ="We judge the open model purely on infrastructure, quality set aside" | F30: =IF(be_devs>0,"Owning accelerators wins above "&TEXT(be_devs,"#,##0")&" developers","Owning still never wins")
B31: ="We count the work the agent cannot finish at all" | F31: =IF(countFallback="Yes","Already counted - it is in the numbers above","Turn it on in Inputs; it usually moves the ranking")
B32: ="Code may not leave our own network" | F32: ="Cost stops being the question"
B33: ="We just want one price per developer, with no surprises" | F33: =planFitName&" at "&TEXT(planFitTeam,"$#,##0")&" a month"
B34: ="We need every developer served at once, without queueing" | F34: =IF(INDEX(Workings!$V$110:$V$119,MATCH(1,r_rank,0))<1,"The cheapest route throttles at "&TEXT(INDEX(Workings!$V$110:$V$119,MATCH(1,r_rank,0)),"0.0")&"x","The cheapest route keeps up")
B36: Chart data - monthly cost by where it goes
B37: Route | C37: Hardware, written down | D37: Power, rack and storage | E37: People to run it | F37: Tokens, seats and rent | G37: Developer time lost
B38: =INDEX(Workings!$A$110:$A$119,MATCH(1,r_rank,0)) | C38: =INDEX(Workings!$C$110:$C$119,MATCH(1,r_rank,0)) | D38: =INDEX(Workings!$D$110:$D$119,MATCH(1,r_rank,0)) | E38: =INDEX(Workings!$E$110:$E$119,MATCH(1,r_rank,0)) | F38: =INDEX(Workings!$F$110:$F$119,MATCH(1,r_rank,0)) | G38: =INDEX(Workings!$G$110:$G$119,MATCH(1,r_rank,0))
B39: =INDEX(Workings!$A$110:$A$119,MATCH(2,r_rank,0)) | C39: =INDEX(Workings!$C$110:$C$119,MATCH(2,r_rank,0)) | D39: =INDEX(Workings!$D$110:$D$119,MATCH(2,r_rank,0)) | E39: =INDEX(Workings!$E$110:$E$119,MATCH(2,r_rank,0)) | F39: =INDEX(Workings!$F$110:$F$119,MATCH(2,r_rank,0)) | G39: =INDEX(Workings!$G$110:$G$119,MATCH(2,r_rank,0))
B40: =INDEX(Workings!$A$110:$A$119,MATCH(3,r_rank,0)) | C40: =INDEX(Workings!$C$110:$C$119,MATCH(3,r_rank,0)) | D40: =INDEX(Workings!$D$110:$D$119,MATCH(3,r_rank,0)) | E40: =INDEX(Workings!$E$110:$E$119,MATCH(3,r_rank,0)) | F40: =INDEX(Workings!$F$110:$F$119,MATCH(3,r_rank,0)) | G40: =INDEX(Workings!$G$110:$G$119,MATCH(3,r_rank,0))
B41: =INDEX(Workings!$A$110:$A$119,MATCH(4,r_rank,0)) | C41: =INDEX(Workings!$C$110:$C$119,MATCH(4,r_rank,0)) | D41: =INDEX(Workings!$D$110:$D$119,MATCH(4,r_rank,0)) | E41: =INDEX(Workings!$E$110:$E$119,MATCH(4,r_rank,0)) | F41: =INDEX(Workings!$F$110:$F$119,MATCH(4,r_rank,0)) | G41: =INDEX(Workings!$G$110:$G$119,MATCH(4,r_rank,0))
B42: =INDEX(Workings!$A$110:$A$119,MATCH(5,r_rank,0)) | C42: =INDEX(Workings!$C$110:$C$119,MATCH(5,r_rank,0)) | D42: =INDEX(Workings!$D$110:$D$119,MATCH(5,r_rank,0)) | E42: =INDEX(Workings!$E$110:$E$119,MATCH(5,r_rank,0)) | F42: =INDEX(Workings!$F$110:$F$119,MATCH(5,r_rank,0)) | G42: =INDEX(Workings!$G$110:$G$119,MATCH(5,r_rank,0))
B43: =INDEX(Workings!$A$110:$A$119,MATCH(6,r_rank,0)) | C43: =INDEX(Workings!$C$110:$C$119,MATCH(6,r_rank,0)) | D43: =INDEX(Workings!$D$110:$D$119,MATCH(6,r_rank,0)) | E43: =INDEX(Workings!$E$110:$E$119,MATCH(6,r_rank,0)) | F43: =INDEX(Workings!$F$110:$F$119,MATCH(6,r_rank,0)) | G43: =INDEX(Workings!$G$110:$G$119,MATCH(6,r_rank,0))
B44: =INDEX(Workings!$A$110:$A$119,MATCH(7,r_rank,0)) | C44: =INDEX(Workings!$C$110:$C$119,MATCH(7,r_rank,0)) | D44: =INDEX(Workings!$D$110:$D$119,MATCH(7,r_rank,0)) | E44: =INDEX(Workings!$E$110:$E$119,MATCH(7,r_rank,0)) | F44: =INDEX(Workings!$F$110:$F$119,MATCH(7,r_rank,0)) | G44: =INDEX(Workings!$G$110:$G$119,MATCH(7,r_rank,0))
B45: =INDEX(Workings!$A$110:$A$119,MATCH(8,r_rank,0)) | C45: =INDEX(Workings!$C$110:$C$119,MATCH(8,r_rank,0)) | D45: =INDEX(Workings!$D$110:$D$119,MATCH(8,r_rank,0)) | E45: =INDEX(Workings!$E$110:$E$119,MATCH(8,r_rank,0)) | F45: =INDEX(Workings!$F$110:$F$119,MATCH(8,r_rank,0)) | G45: =INDEX(Workings!$G$110:$G$119,MATCH(8,r_rank,0))
B46: =INDEX(Workings!$A$110:$A$119,MATCH(9,r_rank,0)) | C46: =INDEX(Workings!$C$110:$C$119,MATCH(9,r_rank,0)) | D46: =INDEX(Workings!$D$110:$D$119,MATCH(9,r_rank,0)) | E46: =INDEX(Workings!$E$110:$E$119,MATCH(9,r_rank,0)) | F46: =INDEX(Workings!$F$110:$F$119,MATCH(9,r_rank,0)) | G46: =INDEX(Workings!$G$110:$G$119,MATCH(9,r_rank,0))
B47: =INDEX(Workings!$A$110:$A$119,MATCH(10,r_rank,0)) | C47: =INDEX(Workings!$C$110:$C$119,MATCH(10,r_rank,0)) | D47: =INDEX(Workings!$D$110:$D$119,MATCH(10,r_rank,0)) | E47: =INDEX(Workings!$E$110:$E$119,MATCH(10,r_rank,0)) | F47: =INDEX(Workings!$F$110:$F$119,MATCH(10,r_rank,0)) | G47: =INDEX(Workings!$G$110:$G$119,MATCH(10,r_rank,0))

Sheet Inputs
A1: Coding assistant - three-year cost of ownership
A2: Offline edition. Change the blue cells; every other sheet recalculates. No macros, no add-ins, nothing to enable.
A4: Blue cells | B4: yours to change - these are the only cells you need to touch
A5: Override column | B5: leave blank to use the catalogue; type a number to beat it
A6: Black cells | B6: formulas - they recalculate, do not type over them
A7: Answer tab | B7: the recommendation, the ranking and the chart
A9: THE THREE CHOICES THAT DECIDE EVERYTHING ELSE
A10: Assumption | B10: Value | C10: Unit | D10: Override | E10: Where it comes from
A11: Open-weight model | B11: gpt-oss 120B-A5.1B | E11: Which weights you would host yourself. Drives memory, fleet size and storage.
A12: Weight precision | B12: FP8 / INT8 | E12: How hard you squeeze the weights. Halving the bytes halves the memory and roughly doubles decode speed.
A13: Accelerator | B13: H100 80GB SXM | E13: The card you would buy or rent.
A14: Flat per-seat plan | B14: Cursor Premium - team | E14: Which subscription the per-seat route prices. Individual plans are in this list too.
A15: Effectiveness profile | B15: Observed - mid-range of published results | E15: How well the models actually do. This is the single biggest lever in the whole model.
A17: TEAM AND WORKLOAD
A18: Assumption | B18: Value | C18: Unit | D18: Override | E18: Where it comes from
A19: Developers | B19: 60 | E19: Everyone who would hold a licence or a session.
A20: Working days | B20: 21 | C20: / mo
A21: Input tokens / dev / day | B21: 10 | C21: M | E21: Agentic coding is input-heavy: the repo, the diff and the tool output go in on every turn.
A22: Output tokens / dev / day | B22: 300 | C22: k | E22: Output is what the accelerators actually spend their time on.
A23: Input served from cache | B23: 0.75 | C23: % | E23: Prompt caching is the largest single discount on any metered route.
A24: Hours in the tool / dev / day | B24: 5 | C24: h
A26: EFFECTIVENESS - THE FAILURE PATH, NOT JUST FIRST PASS
A27: Assumption | B27: Value | C27: Unit | D27: Override | E27: Where it comes from
A28: Frontier first-pass acceptance | B28: =IF($D$28<>"",$D$28,INDEX(tbl_profiles,MATCH(sel_profile,cat_profiles,0),2)) | C28: % | E28: Share of tasks the frontier model gets right first time.
A29: Open first-pass acceptance | B29: =IF($D$29<>"",$D$29,INDEX(tbl_profiles,MATCH(sel_profile,cat_profiles,0),3)) | C29: % | E29: The same for the open model you would host. The gap between these two rows is the whole argument.
A30: Frontier repair success | B30: =IF($D$30<>"",$D$30,INDEX(tbl_profiles,MATCH(sel_profile,cat_profiles,0),4)) | C30: % | E30: A repair pass is worse than the first: the easy wins are already gone.
A31: Open repair success | B31: =IF($D$31<>"",$D$31,INDEX(tbl_profiles,MATCH(sel_profile,cat_profiles,0),5)) | C31: %
A32: Frontier never solves | B32: =IF($D$32<>"",$D$32,INDEX(tbl_profiles,MATCH(sel_profile,cat_profiles,0),6)) | C32: % | E32: Share no number of retries will clear. Retries are spent on these too, which is why retry budgets cost money.
A33: Open never solves | B33: =IF($D$33<>"",$D$33,INDEX(tbl_profiles,MATCH(sel_profile,cat_profiles,0),7)) | C33: %
A34: Accepted tasks / dev / day | B34: 5 | E34: Held constant across routes, which is what makes cost per accepted task comparable.
A35: Developer minutes per attempt | B35: 8 | C35: min | E35: Prompting, waiting, reading the diff.
A36: Repair attempts before giving up | B36: 2
A37: Minutes to write it by hand | B37: 45 | C37: min
A38: Cost the tasks the agent cannot finish | B38: No | E38: Yes charges the human time to finish what the agent abandoned. It usually changes the ranking.
A40: SERVING AND SIZING
A41: Assumption | B41: Value | C41: Unit | D41: Override | E41: Where it comes from
A42: Live context per request | B42: 64 | C42: k tok | E42: Drives the KV cache, which is often larger than people expect.
A43: Concurrent requests / replica | B43: 16
A44: Bandwidth efficiency | B44: 0.65 | C44: % | E44: How much of the card's paper bandwidth a real serving stack reaches.
A45: Single-stream ceiling | B45: 250 | C45: tok/s | E45: Kernel launches, attention and sampling cap one stream far below the weights-read limit.
A46: Checkpoints kept on disk | B46: 3
A47: Developers with a live session | B47: 0.6 | C47: %
A48: Busy hours / day | B48: 8 | C48: h
A49: Peak-to-average | B49: 2 | C49: x | E49: The fleet is sized on the busy hour, not the daily average.
A50: Accelerators per node | B50: 8
A51: Multi-node interconnect loss | B51: 0.2 | C51: % | E51: Crossing a node boundary costs real throughput: the fabric between nodes is far slower than the one inside.
A52: Laptop memory bandwidth | B52: 546 | C52: GB/s | E52: A high-end workstation laptop with unified memory.
A53: Laptop unified memory | B53: 128 | C53: GB
A55: ACCELERATOR
A56: Assumption | B56: Value | C56: Unit | D56: Override | E56: Where it comes from
A57: Memory / card | B57: =IF($D$57<>"",$D$57,INDEX(tbl_gpus,MATCH(sel_gpu,cat_gpus,0),2)) | C57: GB
A58: Memory bandwidth | B58: =IF($D$58<>"",$D$58,INDEX(tbl_gpus,MATCH(sel_gpu,cat_gpus,0),3)) | C58: GB/s | E58: Decode is bandwidth bound, so this sets throughput.
A59: Dense compute | B59: =IF($D$59<>"",$D$59,INDEX(tbl_gpus,MATCH(sel_gpu,cat_gpus,0),4)) | C59: TFLOPS | E59: Prefill is compute bound, so this sets time to first token.
A60: Purchase price / card | B60: =IF($D$60<>"",$D$60,INDEX(tbl_gpus,MATCH(sel_gpu,cat_gpus,0),5)) | C60: $
A61: On-demand rent / card | B61: =IF($D$61<>"",$D$61,INDEX(tbl_gpus,MATCH(sel_gpu,cat_gpus,0),6)) | C61: $/h
A62: Card draw | B62: =IF($D$62<>"",$D$62,INDEX(tbl_gpus,MATCH(sel_gpu,cat_gpus,0),7)) | C62: W
A63: Host, NIC, fabric / 8 cards | B63: 45000 | C63: $
A64: Rented fleet uptime | B64: 0.7 | C64: % | E64: Rented cards bill by the hour whether they are busy or idle.
A66: FACILITY AND LAPTOPS
A67: Assumption | B67: Value | C67: Unit | D67: Override | E67: Where it comes from
A68: Datacentre PUE | B68: 1.4 | C68: x | E68: Power drawn per watt delivered to the card.
A69: Datacentre electricity | B69: 0.1 | C69: $/kWh
A70: Rack space and cooling | B70: 200 | C70: $/kW/mo
A71: Model storage | B71: 0.08 | C71: $/GB/mo
A72: Laptop uplift / dev | B72: 3000 | C72: $ | E72: What the memory-heavy machine costs over the standard issue.
A73: Laptop draw while running | B73: 90 | C73: W
A74: Laptop fiddling / dev / yr | B74: 6 | C74: h
A75: IT support cost | B75: 75 | C75: $/h
A76: Office electricity | B76: 0.14 | C76: $/kWh
A78: BUILD AND LABOUR
A79: Assumption | B79: Value | C79: Unit | D79: Override | E79: Where it comes from
A80: Count setup and running labour | B80: Yes | E80: No strips every hour of human time out of the comparison. It flatters self-hosting heavily.
A81: Fabric, optics and cabling | B81: 12000 | C81: $/host
A82: Rack, PDU and smart hands | B82: 3500 | C82: $/host
A83: Spare cards held | B83: 0.05 | C83: % of fleet
A84: Hardware support | B84: 0.1 | C84: %/yr of capex
A85: Architecture and procurement | B85: 80 | C85: h
A86: Rack, cable and bring-up | B86: 60 | C86: h/host
A87: Serving stack and cluster | B87: 120 | C87: h
A88: Model evaluation | B88: 80 | C88: h
A89: Security and compliance review | B89: 60 | C89: h
A91: MONEY AND PEOPLE
A92: Assumption | B92: Value | C92: Unit | D92: Override | E92: Where it comes from
A93: Horizon | B93: 36 | C93: mo
A94: Hardware write-off | B94: 36 | C94: mo
A95: Loaded developer cost | B95: 95 | C95: $/h
A96: Loaded platform engineer | B96: 260000 | C96: $/yr
A97: Baseline AI platform team | B97: 0.5 | C97: FTE | E97: Gateway, secrets, IAM, observability, evals and cost control. Every centralised route pays this, not just the cloud ones.
A98: Full platform team at | B98: 20 | C98: devs | E98: Staffing ramps with headcount and reaches full strength here. A solo developer does not employ a fifth of an engineer.
A99: Small-team advice up to | B99: 3 | C99: devs | E99: At or below this the recommendation talks about subscriptions instead of platforms.
A100: Platform engineers on the fleet | B100: 0.4 | C100: FTE
A101: Cloud plumbing staff | B101: 0.15 | C101: FTE
A102: We already run an AI platform | B102: No | E102: Yes charges no baseline platform team, because you already pay for it.
A103: Negotiated API discount | B103: 0 | C103: % | E103: Applies to metered tokens only, never to seats.
A105: RATE CARDS
A106: Assumption | B106: Value | C106: Unit | D106: Override | E106: Where it comes from
A107: Anthropic - input | B107: 2 | C107: $/M
A108: Anthropic - output | B108: 10 | C108: $/M
A109: Anthropic - cache read | B109: 0.2 | C109: $/M
A110: Anthropic ceiling | B110: 2000 | C110: k tok/min
...

Sheet Models
A1: Which model, at your workload
A2: The same month of work, priced on every candidate. Rate cards are list prices from Catalogues; the self-hosted block replays the whole fleet calculation once per set of weights, because changing the model changes the iron under it.
A4: PAY PER TOKEN
A5: Model | B5: Lab | C5: In $/M | D5: Out $/M | E5: Your bill / mo | F5: AI $ / task | G5: vs cheapest
A6: =Catalogues!$A$52 | B6: =Catalogues!$B$52 | C6: =Catalogues!$C$52 | D6: =Catalogues!$D$52 | E6: =(m_fresh/1000000*C6+m_cached/1000000*Catalogues!$E$52+m_outTok/1000000*D6)*disc | F6: =IF(acceptedTasks>0,E6/acceptedTasks,0) | G6: =IF(MIN($E$6:$E$10)>0,E6/MIN($E$6:$E$10),0)
A7: =Catalogues!$A$53 | B7: =Catalogues!$B$53 | C7: =Catalogues!$C$53 | D7: =Catalogues!$D$53 | E7: =(m_fresh/1000000*C7+m_cached/1000000*Catalogues!$E$53+m_outTok/1000000*D7)*disc | F7: =IF(acceptedTasks>0,E7/acceptedTasks,0) | G7: =IF(MIN($E$6:$E$10)>0,E7/MIN($E$6:$E$10),0)
A8: =Catalogues!$A$54 | B8: =Catalogues!$B$54 | C8: =Catalogues!$C$54 | D8: =Catalogues!$D$54 | E8: =(m_fresh/1000000*C8+m_cached/1000000*Catalogues!$E$54+m_outTok/1000000*D8)*disc | F8: =IF(acceptedTasks>0,E8/acceptedTasks,0) | G8: =IF(MIN($E$6:$E$10)>0,E8/MIN($E$6:$E$10),0)
A9: =Catalogues!$A$55 | B9: =Catalogues!$B$55 | C9: =Catalogues!$C$55 | D9: =Catalogues!$D$55 | E9: =(m_fresh/1000000*C9+m_cached/1000000*Catalogues!$E$55+m_outTok/1000000*D9)*disc | F9: =IF(acceptedTasks>0,E9/acceptedTasks,0) | G9: =IF(MIN($E$6:$E$10)>0,E9/MIN($E$6:$E$10),0)
A10: Open weights, serverless | B10: aggregator or provider | C10: =orIn | D10: =orOut | E10: =(m_fresh*tm_o/1000000*orIn+m_cached*tm_o/1000000*orCache+m_outTok*tm_o/1000000*orOut)*disc*(1+orFee) | F10: =IF(acceptedTasks>0,E10/acceptedTasks,0) | G10: =IF(MIN($E$6:$E$10)>0,E10/MIN($E$6:$E$10),0)
A11: The serverless row carries the open model's extra attempts, because a weaker model needs more of them for the same accepted work. The frontier rows are the yardstick at 1.00x.
A13: HOST IT YOURSELF - THE WHOLE FLEET CALCULATION, ONCE PER MODEL
A14: Open-weight model | B14: Weights GB | C14: KV GB | D14: Memory / replica | E14: Cards / replica | F14: Replicas | G14: Cards | H14: Hosts | I14: One replica tok/s | J14: Hardware capital | K14: Written down | L14: Power & rack | M14: People | N14: Developer time | O14: Own it / mo | P14: vs cheapest | Q14: Fits a laptop
A15: =Catalogues!$A$6 | B15: =Catalogues!$B$6*q_bytes | C15: =batch*ctxK*1000*Catalogues!$D$6*q_kv/1024 | D15: =B15*1.15+C15 | E15: =IF(MAX(1,CEILING(D15/MAX(1,gpuVram),1))<=nodeSize,MIN(nodeSize,POWER(2,CEILING(LOG(MAX(1,CEILING(D15/MAX(1,gpuVram),1)),2)-0.0000001,1))),CEILING(MAX(1,CEILING(D15/MAX(1,gpuVram),1))/nodeSize,1)*nodeSize) | F15: =IF(devs=0,0,IF(I15>0,MAX(1,CEILING(peakTps/I15,1)),1)) | G15: =F15*E15 | H15: =CEILING(G15/8,1) | I15: =MIN(E15*MAX(1,gpuBw)*IF(CEILING(E15/nodeSize,1)>1,MAX(0.05,1-multiNodeLoss),1)/(Catalogues!$C$6*q_bytes)*bwEff,streamCap)*MIN(batch,32) | J15: =G15*gpuBuy*(1+spares)+H15*(hostCost+netFabric+installHost) | K15: =J15/amort | L15: =G15*gpuW/1000*1.25*(pue*730*kwhDc+coloKw)+(Catalogues!$B$6*2+Catalogues!$B$6*q_bytes)*MAX(1,ckpts)*storGb+J15*warranty/12 | M15: =platformMo+adminMo+IF(labourYN="Yes",(setupArch+H15*setupRack+setupStack+setupEval+setupSec)*engHr,0)/amort | N15: =drag_o | O15: =K15+L15+M15+N15 | P15: =IF(MIN($O$15:$O$24)>0,O15/MIN($O$15:$O$24),0) | Q15: =IF(B15*1.15+4<=lapRam,"Yes","No")
A16: =Catalogues!$A$7 | B16: =Catalogues!$B$7*q_bytes | C16: =batch*ctxK*1000*Catalogues!$D$7*q_kv/1024 | D16: =B16*1.15+C16 | E16: =IF(MAX(1,CEILING(D16/MAX(1,gpuVram),1))<=nodeSize,MIN(nodeSize,POWER(2,CEILING(LOG(MAX(1,CEILING(D16/MAX(1,gpuVram),1)),2)-0.0000001,1))),CEILING(MAX(1,CEILING(D16/MAX(1,gpuVram),1))/nodeSize,1)*nodeSize) | F16: =IF(devs=0,0,IF(I16>0,MAX(1,CEILING(peakTps/I16,1)),1)) | G16: =F16*E16 | H16: =CEILING(G16/8,1) | I16: =MIN(E16*MAX(1,gpuBw)*IF(CEILING(E16/nodeSize,1)>1,MAX(0.05,1-multiNodeLoss),1)/(Catalogues!$C$7*q_bytes)*bwEff,streamCap)*MIN(batch,32) | J16: =G16*gpuBuy*(1+spares)+H16*(hostCost+netFabric+installHost) | K16: =J16/amort | L16: =G16*gpuW/1000*1.25*(pue*730*kwhDc+coloKw)+(Catalogues!$B$7*2+Catalogues!$B$7*q_bytes)*MAX(1,ckpts)*storGb+J16*warranty/12 | M16: =platformMo+adminMo+IF(labourYN="Yes",(setupArch+H16*setupRack+setupStack+setupEval+setupSec)*engHr,0)/amort | N16: =drag_o | O16: =K16+L16+M16+N16 | P16: =IF(MIN($O$15:$O$24)>0,O16/MIN($O$15:$O$24),0) | Q16: =IF(B16*1.15+4<=lapRam,"Yes","No")
A17: =Catalogues!$A$8 | B17: =Catalogues!$B$8*q_bytes | C17: =batch*ctxK*1000*Catalogues!$D$8*q_kv/1024 | D17: =B17*1.15+C17 | E17: =IF(MAX(1,CEILING(D17/MAX(1,gpuVram),1))<=nodeSize,MIN(nodeSize,POWER(2,CEILING(LOG(MAX(1,CEILING(D17/MAX(1,gpuVram),1)),2)-0.0000001,1))),CEILING(MAX(1,CEILING(D17/MAX(1,gpuVram),1))/nodeSize,1)*nodeSize) | F17: =IF(devs=0,0,IF(I17>0,MAX(1,CEILING(peakTps/I17,1)),1)) | G17: =F17*E17 | H17: =CEILING(G17/8,1) | I17: =MIN(E17*MAX(1,gpuBw)*IF(CEILING(E17/nodeSize,1)>1,MAX(0.05,1-multiNodeLoss),1)/(Catalogues!$C$8*q_bytes)*bwEff,streamCap)*MIN(batch,32) | J17: =G17*gpuBuy*(1+spares)+H17*(hostCost+netFabric+installHost) | K17: =J17/amort | L17: =G17*gpuW/1000*1.25*(pue*730*kwhDc+coloKw)+(Catalogues!$B$8*2+Catalogues!$B$8*q_bytes)*MAX(1,ckpts)*storGb+J17*warranty/12 | M17: =platformMo+adminMo+IF(labourYN="Yes",(setupArch+H17*setupRack+setupStack+setupEval+setupSec)*engHr,0)/amort | N17: =drag_o | O17: =K17+L17+M17+N17 | P17: =IF(MIN($O$15:$O$24)>0,O17/MIN($O$15:$O$24),0) | Q17: =IF(B17*1.15+4<=lapRam,"Yes","No")
A18: =Catalogues!$A$9 | B18: =Catalogues!$B$9*q_bytes | C18: =batch*ctxK*1000*Catalogues!$D$9*q_kv/1024 | D18: =B18*1.15+C18 | E18: =IF(MAX(1,CEILING(D18/MAX(1,gpuVram),1))<=nodeSize,MIN(nodeSize,POWER(2,CEILING(LOG(MAX(1,CEILING(D18/MAX(1,gpuVram),1)),2)-0.0000001,1))),CEILING(MAX(1,CEILING(D18/MAX(1,gpuVram),1))/nodeSize,1)*nodeSize) | F18: =IF(devs=0,0,IF(I18>0,MAX(1,CEILING(peakTps/I18,1)),1)) | G18: =F18*E18 | H18: =CEILING(G18/8,1) | I18: =MIN(E18*MAX(1,gpuBw)*IF(CEILING(E18/nodeSize,1)>1,MAX(0.05,1-multiNodeLoss),1)/(Catalogues!$C$9*q_bytes)*bwEff,streamCap)*MIN(batch,32) | J18: =G18*gpuBuy*(1+spares)+H18*(hostCost+netFabric+installHost) | K18: =J18/amort | L18: =G18*gpuW/1000*1.25*(pue*730*kwhDc+coloKw)+(Catalogues!$B$9*2+Catalogues!$B$9*q_bytes)*MAX(1,ckpts)*storGb+J18*warranty/12 | M18: =platformMo+adminMo+IF(labourYN="Yes",(setupArch+H18*setupRack+setupStack+setupEval+setupSec)*engHr,0)/amort | N18: =drag_o | O18: =K18+L18+M18+N18 | P18: =IF(MIN($O$15:$O$24)>0,O18/MIN($O$15:$O$24),0) | Q18: =IF(B18*1.15+4<=lapRam,"Yes","No")
A19: =Catalogues!$A$10 | B19: =Catalogues!$B$10*q_bytes | C19: =batch*ctxK*1000*Catalogues!$D$10*q_kv/1024 | D19: =B19*1.15+C19 | E19: =IF(MAX(1,CEILING(D19/MAX(1,gpuVram),1))<=nodeSize,MIN(nodeSize,POWER(2,CEILING(LOG(MAX(1,CEILING(D19/MAX(1,gpuVram),1)),2)-0.0000001,1))),CEILING(MAX(1,CEILING(D19/MAX(1,gpuVram),1))/nodeSize,1)*nodeSize) | F19: =IF(devs=0,0,IF(I19>0,MAX(1,CEILING(peakTps/I19,1)),1)) | G19: =F19*E19 | H19: =CEILING(G19/8,1) | I19: =MIN(E19*MAX(1,gpuBw)*IF(CEILING(E19/nodeSize,1)>1,MAX(0.05,1-multiNodeLoss),1)/(Catalogues!$C$10*q_bytes)*bwEff,streamCap)*MIN(batch,32) | J19: =G19*gpuBuy*(1+spares)+H19*(hostCost+netFabric+installHost) | K19: =J19/amort | L19: =G19*gpuW/1000*1.25*(pue*730*kwhDc+coloKw)+(Catalogues!$B$10*2+Catalogues!$B$10*q_bytes)*MAX(1,ckpts)*storGb+J19*warranty/12 | M19: =platformMo+adminMo+IF(labourYN="Yes",(setupArch+H19*setupRack+setupStack+setupEval+setupSec)*engHr,0)/amort | N19: =drag_o | O19: =K19+L19+M19+N19 | P19: =IF(MIN($O$15:$O$24)>0,O19/MIN($O$15:$O$24),0) | Q19: =IF(B19*1.15+4<=lapRam,"Yes","No")
A20: =Catalogues!$A$11 | B20: =Catalogues!$B$11*q_bytes | C20: =batch*ctxK*1000*Catalogues!$D$11*q_kv/1024 | D20: =B20*1.15+C20 | E20: =IF(MAX(1,CEILING(D20/MAX(1,gpuVram),1))<=nodeSize,MIN(nodeSize,POWER(2,CEILING(LOG(MAX(1,CEILING(D20/MAX(1,gpuVram),1)),2)-0.0000001,1))),CEILING(MAX(1,CEILING(D20/MAX(1,gpuVram),1))/nodeSize,1)*nodeSize) | F20: =IF(devs=0,0,IF(I20>0,MAX(1,CEILING(peakTps/I20,1)),1)) | G20: =F20*E20 | H20: =CEILING(G20/8,1) | I20: =MIN(E20*MAX(1,gpuBw)*IF(CEILING(E20/nodeSize,1)>1,MAX(0.05,1-multiNodeLoss),1)/(Catalogues!$C$11*q_bytes)*bwEff,streamCap)*MIN(batch,32) | J20: =G20*gpuBuy*(1+spares)+H20*(hostCost+netFabric+installHost) | K20: =J20/amort | L20: =G20*gpuW/1000*1.25*(pue*730*kwhDc+coloKw)+(Catalogues!$B$11*2+Catalogues!$B$11*q_bytes)*MAX(1,ckpts)*storGb+J20*warranty/12 | M20: =platformMo+adminMo+IF(labourYN="Yes",(setupArch+H20*setupRack+setupStack+setupEval+setupSec)*engHr,0)/amort | N20: =drag_o | O20: =K20+L20+M20+N20 | P20: =IF(MIN($O$15:$O$24)>0,O20/MIN($O$15:$O$24),0) | Q20: =IF(B20*1.15+4<=lapRam,"Yes","No")
A21: =Catalogues!$A$12 | B21: =Catalogues!$B$12*q_bytes | C21: =batch*ctxK*1000*Catalogues!$D$12*q_kv/1024 | D21: =B21*1.15+C21 | E21: =IF(MAX(1,CEILING(D21/MAX(1,gpuVram),1))<=nodeSize,MIN(nodeSize,POWER(2,CEILING(LOG(MAX(1,CEILING(D21/MAX(1,gpuVram),1)),2)-0.0000001,1))),CEILING(MAX(1,CEILING(D21/MAX(1,gpuVram),1))/nodeSize,1)*nodeSize) | F21: =IF(devs=0,0,IF(I21>0,MAX(1,CEILING(peakTps/I21,1)),1)) | G21: =F21*E21 | H21: =CEILING(G21/8,1) | I21: =MIN(E21*MAX(1,gpuBw)*IF(CEILING(E21/nodeSize,1)>1,MAX(0.05,1-multiNodeLoss),1)/(Catalogues!$C$12*q_bytes)*bwEff,streamCap)*MIN(batch,32) | J21: =G21*gpuBuy*(1+spares)+H21*(hostCost+netFabric+installHost) | K21: =J21/amort | L21: =G21*gpuW/1000*1.25*(pue*730*kwhDc+coloKw)+(Catalogues!$B$12*2+Catalogues!$B$12*q_bytes)*MAX(1,ckpts)*storGb+J21*warranty/12 | M21: =platformMo+adminMo+IF(labourYN="Yes",(setupArch+H21*setupRack+setupStack+setupEval+setupSec)*engHr,0)/amort | N21: =drag_o | O21: =K21+L21+M21+N21 | P21: =IF(MIN($O$15:$O$24)>0,O21/MIN($O$15:$O$24),0) | Q21: =IF(B21*1.15+4<=lapRam,"Yes","No")
A22: =Catalogues!$A$13 | B22: =Catalogues!$B$13*q_bytes | C22: =batch*ctxK*1000*Catalogues!$D$13*q_kv/1024 | D22: =B22*1.15+C22 | E22: =IF(MAX(1,CEILING(D22/MAX(1,gpuVram),1))<=nodeSize,MIN(nodeSize,POWER(2,CEILING(LOG(MAX(1,CEILING(D22/MAX(1,gpuVram),1)),2)-0.0000001,1))),CEILING(MAX(1,CEILING(D22/MAX(1,gpuVram),1))/nodeSize,1)*nodeSize) | F22: =IF(devs=0,0,IF(I22>0,MAX(1,CEILING(peakTps/I22,1)),1)) | G22: =F22*E22 | H22: =CEILING(G22/8,1) | I22: =MIN(E22*MAX(1,gpuBw)*IF(CEILING(E22/nodeSize,1)>1,MAX(0.05,1-multiNodeLoss),1)/(Catalogues!$C$13*q_bytes)*bwEff,streamCap)*MIN(batch,32) | J22: =G22*gpuBuy*(1+spares)+H22*(hostCost+netFabric+installHost) | K22: =J22/amort | L22: =G22*gpuW/1000*1.25*(pue*730*kwhDc+coloKw)+(Catalogues!$B$13*2+Catalogues!$B$13*q_bytes)*MAX(1,ckpts)*storGb+J22*warranty/12 | M22: =platformMo+adminMo+IF(labourYN="Yes",(setupArch+H22*setupRack+setupStack+setupEval+setupSec)*engHr,0)/amort | N22: =drag_o | O22: =K22+L22+M22+N22 | P22: =IF(MIN($O$15:$O$24)>0,O22/MIN($O$15:$O$24),0) | Q22: =IF(B22*1.15+4<=lapRam,"Yes","No")
A23: =Catalogues!$A$14 | B23: =Catalogues!$B$14*q_bytes | C23: =batch*ctxK*1000*Catalogues!$D$14*q_kv/1024 | D23: =B23*1.15+C23 | E23: =IF(MAX(1,CEILING(D23/MAX(1,gpuVram),1))<=nodeSize,MIN(nodeSize,POWER(2,CEILING(LOG(MAX(1,CEILING(D23/MAX(1,gpuVram),1)),2)-0.0000001,1))),CEILING(MAX(1,CEILING(D23/MAX(1,gpuVram),1))/nodeSize,1)*nodeSize) | F23: =IF(devs=0,0,IF(I23>0,MAX(1,CEILING(peakTps/I23,1)),1)) | G23: =F23*E23 | H23: =CEILING(G23/8,1) | I23: =MIN(E23*MAX(1,gpuBw)*IF(CEILING(E23/nodeSize,1)>1,MAX(0.05,1-multiNodeLoss),1)/(Catalogues!$C$14*q_bytes)*bwEff,streamCap)*MIN(batch,32) | J23: =G23*gpuBuy*(1+spares)+H23*(hostCost+netFabric+installHost) | K23: =J23/amort | L23: =G23*gpuW/1000*1.25*(pue*730*kwhDc+coloKw)+(Catalogues!$B$14*2+Catalogues!$B$14*q_bytes)*MAX(1,ckpts)*storGb+J23*warranty/12 | M23: =platformMo+adminMo+IF(labourYN="Yes",(setupArch+H23*setupRack+setupStack+setupEval+setupSec)*engHr,0)/amort | N23: =drag_o | O23: =K23+L23+M23+N23 | P23: =IF(MIN($O$15:$O$24)>0,O23/MIN($O$15:$O$24),0) | Q23: =IF(B23*1.15+4<=lapRam,"Yes","No")
A24: =Catalogues!$A$15 | B24: =Catalogues!$B$15*q_bytes | C24: =batch*ctxK*1000*Catalogues!$D$15*q_kv/1024 | D24: =B24*1.15+C24 | E24: =IF(MAX(1,CEILING(D24/MAX(1,gpuVram),1))<=nodeSize,MIN(nodeSize,POWER(2,CEILING(LOG(MAX(1,CEILING(D24/MAX(1,gpuVram),1)),2)-0.0000001,1))),CEILING(MAX(1,CEILING(D24/MAX(1,gpuVram),1))/nodeSize,1)*nodeSize) | F24: =IF(devs=0,0,IF(I24>0,MAX(1,CEILING(peakTps/I24,1)),1)) | G24: =F24*E24 | H24: =CEILING(G24/8,1) | I24: =MIN(E24*MAX(1,gpuBw)*IF(CEILING(E24/nodeSize,1)>1,MAX(0.05,1-multiNodeLoss),1)/(Catalogues!$C$15*q_bytes)*bwEff,streamCap)*MIN(batch,32) | J24: =G24*gpuBuy*(1+spares)+H24*(hostCost+netFabric+installHost) | K24: =J24/amort | L24: =G24*gpuW/1000*1.25*(pue*730*kwhDc+coloKw)+(Catalogues!$B$15*2+Catalogues!$B$15*q_bytes)*MAX(1,ckpts)*storGb+J24*warranty/12 | M24: =platformMo+adminMo+IF(labourYN="Yes",(setupArch+H24*setupRack+setupStack+setupEval+setupSec)*engHr,0)/amort | N24: =drag_o | O24: =K24+L24+M24+N24 | P24: =IF(MIN($O$15:$O$24)>0,O24/MIN($O$15:$O$24),0) | Q24: =IF(B24*1.15+4<=lapRam,"Yes","No")
A25: Fleet size is driven by peak demand, which does not change with the model - what changes is how much iron it takes to meet it. The cheapest weights to run are rarely the cheapest weights to own.
A27: Cheapest to own | B27: =INDEX($A$15:$A$24,MATCH(MIN($O$15:$O$24),$O$15:$O$24,0))
A28: Cheapest per token | B28: =INDEX($A$6:$A$10,MATCH(MIN($E$6:$E$10),$E$6:$E$10,0))

Sheet Scale
A1: How the answer changes with team size
A2: Every input is exactly as you left it on Inputs - only the head count moves. This is where the break-even lives.
A4: TEAM SIZE
A5: Developers | B5: edit these if you like | C5: 1 | D5: 2 | E5: 5 | F5: 10 | G5: 25 | H5: 50 | I5: 100 | J5: 200 | K5: 350 | L5: 500 | M5: 750 | N5: 1000
A7: VOLUMES, FLEET AND STAFFING AT EACH SIZE
A8: Output tokens / mo | C8: =C$5*outTok*1000*workdays | D8: =D$5*outTok*1000*workdays | E8: =E$5*outTok*1000*workdays | F8: =F$5*outTok*1000*workdays | G8: =G$5*outTok*1000*workdays | H8: =H$5*outTok*1000*workdays | I8: =I$5*outTok*1000*workdays | J8: =J$5*outTok*1000*workdays | ... N8: =N$5*outTok*1000*workdays
A9: Input tokens / mo | C9: =C$5*inTok*1000000*workdays | D9: =D$5*inTok*1000000*workdays | E9: =E$5*inTok*1000000*workdays | F9: =F$5*inTok*1000000*workdays | G9: =G$5*inTok*1000000*workdays | H9: =H$5*inTok*1000000*workdays | I9: =I$5*inTok*1000000*workdays | J9: =J$5*inTok*1000000*workdays | ... N9: =N$5*inTok*1000000*workdays
A10: Cached input | C10: =C$9*MIN(1,cacheShare) | D10: =D$9*MIN(1,cacheShare) | E10: =E$9*MIN(1,cacheShare) | F10: =F$9*MIN(1,cacheShare) | G10: =G$9*MIN(1,cacheShare) | H10: =H$9*MIN(1,cacheShare) | I10: =I$9*MIN(1,cacheShare) | J10: =J$9*MIN(1,cacheShare) | ... N10: =N$9*MIN(1,cacheShare)
A11: Fresh input | C11: =C$9-C$10 | D11: =D$9-D$10 | E11: =E$9-E$10 | F11: =F$9-F$10 | G11: =G$9-G$10 | H11: =H$9-H$10 | I11: =I$9-I$10 | J11: =J$9-J$10 | ... N11: =N$9-N$10
A12: Accepted tasks / mo | C12: =C$5*tasksDay*workdays | D12: =D$5*tasksDay*workdays | E12: =E$5*tasksDay*workdays | F12: =F$5*tasksDay*workdays | G12: =G$5*tasksDay*workdays | H12: =H$5*tasksDay*workdays | I12: =I$5*tasksDay*workdays | J12: =J$5*tasksDay*workdays | ... N12: =N$5*tasksDay*workdays
A13: Live sessions at once | C13: =C$5*sessConc | D13: =D$5*sessConc | E13: =E$5*sessConc | F13: =F$5*sessConc | G13: =G$5*sessConc | H13: =H$5*sessConc | I13: =I$5*sessConc | J13: =J$5*sessConc | ... N13: =N$5*sessConc
A14: Peak demand, open model | B14: tok/s in the busy hour | C14: =IF(AND(workdays>0,activeHrs>0),C$8*tm_o/workdays/(activeHrs*3600)*peak,0) | D14: =IF(AND(workdays>0,activeHrs>0),D$8*tm_o/workdays/(activeHrs*3600)*peak,0) | E14: =IF(AND(workdays>0,activeHrs>0),E$8*tm_o/workdays/(activeHrs*3600)*peak,0) | F14: =IF(AND(workdays>0,activeHrs>0),F$8*tm_o/workdays/(activeHrs*3600)*peak,0) | G14: =IF(AND(workdays>0,activeHrs>0),G$8*tm_o/workdays/(activeHrs*3600)*peak,0) | H14: =IF(AND(workdays>0,activeHrs>0),H$8*tm_o/workdays/(activeHrs*3600)*peak,0) | I14: =IF(AND(workdays>0,activeHrs>0),I$8*tm_o/workdays/(activeHrs*3600)*peak,0) | J14: =IF(AND(workdays>0,activeHrs>0),J$8*tm_o/workdays/(activeHrs*3600)*peak,0) | ... N14: =IF(AND(workdays>0,activeHrs>0),N$8*tm_o/workdays/(activeHrs*3600)*peak,0)
A15: Replicas | C15: =IF(C$5=0,0,IF(replicaTps>0,MAX(1,CEILING(C$14/replicaTps,1)),1)) | D15: =IF(D$5=0,0,IF(replicaTps>0,MAX(1,CEILING(D$14/replicaTps,1)),1)) | E15: =IF(E$5=0,0,IF(replicaTps>0,MAX(1,CEILING(E$14/replicaTps,1)),1)) | F15: =IF(F$5=0,0,IF(replicaTps>0,MAX(1,CEILING(F$14/replicaTps,1)),1)) | G15: =IF(G$5=0,0,IF(replicaTps>0,MAX(1,CEILING(G$14/replicaTps,1)),1)) | H15: =IF(H$5=0,0,IF(replicaTps>0,MAX(1,CEILING(H$14/replicaTps,1)),1)) | I15: =IF(I$5=0,0,IF(replicaTps>0,MAX(1,CEILING(I$14/replicaTps,1)),1)) | J15: =IF(J$5=0,0,IF(replicaTps>0,MAX(1,CEILING(J$14/replicaTps,1)),1)) | ... N15: =IF(N$5=0,0,IF(replicaTps>0,MAX(1,CEILING(N$14/replicaTps,1)),1))
A16: Cards in the fleet | C16: =C$15*gpusPerReplica | D16: =D$15*gpusPerReplica | E16: =E$15*gpusPerReplica | F16: =F$15*gpusPerReplica | G16: =G$15*gpusPerReplica | H16: =H$15*gpusPerReplica | I16: =I$15*gpusPerReplica | J16: =J$15*gpusPerReplica | ... N16: =N$15*gpusPerReplica
A17: Hosts | C17: =CEILING(C$16/8,1) | D17: =CEILING(D$16/8,1) | E17: =CEILING(E$16/8,1) | F17: =CEILING(F$16/8,1) | G17: =CEILING(G$16/8,1) | H17: =CEILING(H$16/8,1) | I17: =CEILING(I$16/8,1) | J17: =CEILING(J$16/8,1) | ... N17: =CEILING(N$16/8,1)
A18: Sustained fleet tok/s | C18: =C$15*replicaTps | D18: =D$15*replicaTps | E18: =E$15*replicaTps | F18: =F$15*replicaTps | G18: =G$15*replicaTps | H18: =H$15*replicaTps | I18: =I$15*replicaTps | J18: =J$15*replicaTps | ... N18: =N$15*replicaTps
A19: Hardware capital | C19: =C$16*gpuBuy*(1+spares)+C$17*(hostCost+netFabric+installHost) | D19: =D$16*gpuBuy*(1+spares)+D$17*(hostCost+netFabric+installHost) | E19: =E$16*gpuBuy*(1+spares)+E$17*(hostCost+netFabric+installHost) | F19: =F$16*gpuBuy*(1+spares)+F$17*(hostCost+netFabric+installHost) | G19: =G$16*gpuBuy*(1+spares)+G$17*(hostCost+netFabric+installHost) | H19: =H$16*gpuBuy*(1+spares)+H$17*(hostCost+netFabric+installHost) | I19: =I$16*gpuBuy*(1+spares)+I$17*(hostCost+netFabric+installHost) | J19: =J$16*gpuBuy*(1+spares)+J$17*(hostCost+netFabric+installHost) | ... N19: =N$16*gpuBuy*(1+spares)+N$17*(hostCost+netFabric+installHost)
A20: Setup labour | C20: =IF(labourYN="Yes",(setupArch+C$17*setupRack+setupStack+setupEval+setupSec)*engHr,0) | D20: =IF(labourYN="Yes",(setupArch+D$17*setupRack+setupStack+setupEval+setupSec)*engHr,0) | E20: =IF(labourYN="Yes",(setupArch+E$17*setupRack+setupStack+setupEval+setupSec)*engHr,0) | F20: =IF(labourYN="Yes",(setupArch+F$17*setupRack+setupStack+setupEval+setupSec)*engHr,0) | G20: =IF(labourYN="Yes",(setupArch+G$17*setupRack+setupStack+setupEval+setupSec)*engHr,0) | H20: =IF(labourYN="Yes",(setupArch+H$17*setupRack+setupStack+setupEval+setupSec)*engHr,0) | I20: =IF(labourYN="Yes",(setupArch+I$17*setupRack+setupStack+setupEval+setupSec)*engHr,0) | J20: =IF(labourYN="Yes",(setupArch+J$17*setupRack+setupStack+setupEval+setupSec)*engHr,0) | ... N20: =IF(labourYN="Yes",(setupArch+N$17*setupRack+setupStack+setupEval+setupSec)*engHr,0)
A21: Staffing ramp | C21: =IF(platformAt>soloAt,MIN(1,MAX(0,(C$5-soloAt)/(platformAt-soloAt))),IF(C$5>soloAt,1,0)) | D21: =IF(platformAt>soloAt,MIN(1,MAX(0,(D$5-soloAt)/(platformAt-soloAt))),IF(D$5>soloAt,1,0)) | E21: =IF(platformAt>soloAt,MIN(1,MAX(0,(E$5-soloAt)/(platformAt-soloAt))),IF(E$5>soloAt,1,0)) | F21: =IF(platformAt>soloAt,MIN(1,MAX(0,(F$5-soloAt)/(platformAt-soloAt))),IF(F$5>soloAt,1,0)) | G21: =IF(platformAt>soloAt,MIN(1,MAX(0,(G$5-soloAt)/(platformAt-soloAt))),IF(G$5>soloAt,1,0)) | H21: =IF(platformAt>soloAt,MIN(1,MAX(0,(H$5-soloAt)/(platformAt-soloAt))),IF(H$5>soloAt,1,0)) | I21: =IF(platformAt>soloAt,MIN(1,MAX(0,(I$5-soloAt)/(platformAt-soloAt))),IF(I$5>soloAt,1,0)) | J21: =IF(platformAt>soloAt,MIN(1,MAX(0,(J$5-soloAt)/(platformAt-soloAt))),IF(J$5>soloAt,1,0)) | ... N21: =IF(platformAt>soloAt,MIN(1,MAX(0,(N$5-soloAt)/(platformAt-soloAt))),IF(N$5>soloAt,1,0))
A22: Baseline platform team | C22: =IF(AND(labourYN="Yes",ownsPlatform="No"),platformFte*fteMo*C$21,0) | D22: =IF(AND(labourYN="Yes",ownsPlatform="No"),platformFte*fteMo*D$21,0) | E22: =IF(AND(labourYN="Yes",ownsPlatform="No"),platformFte*fteMo*E$21,0) | F22: =IF(AND(labourYN="Yes",ownsPlatform="No"),platformFte*fteMo*F$21,0) | G22: =IF(AND(labourYN="Yes",ownsPlatform="No"),platformFte*fteMo*G$21,0) | H22: =IF(AND(labourYN="Yes",ownsPlatform="No"),platformFte*fteMo*H$21,0) | I22: =IF(AND(labourYN="Yes",ownsPlatform="No"),platformFte*fteMo*I$21,0) | J22: =IF(AND(labourYN="Yes",ownsPlatform="No"),platformFte*fteMo*J$21,0) | ... N22: =IF(AND(labourYN="Yes",ownsPlatform="No"),platformFte*fteMo*N$21,0)
A23: Fleet admin | C23: =IF(labourYN="Yes",adminFte*fteMo*C$21,0) | D23: =IF(labourYN="Yes",adminFte*fteMo*D$21,0) | E23: =IF(labourYN="Yes",adminFte*fteMo*E$21,0) | F23: =IF(labourYN="Yes",adminFte*fteMo*F$21,0) | G23: =IF(labourYN="Yes",adminFte*fteMo*G$21,0) | H23: =IF(labourYN="Yes",adminFte*fteMo*H$21,0) | I23: =IF(labourYN="Yes",adminFte*fteMo*I$21,0) | J23: =IF(labourYN="Yes",adminFte*fteMo*J$21,0) | ... N23: =IF(labourYN="Yes",adminFte*fteMo*N$21,0)
A24: Cloud plumbing | C24: =IF(labourYN="Yes",cloudOps*fteMo*C$21,0) | D24: =IF(labourYN="Yes",cloudOps*fteMo*D$21,0) | E24: =IF(labourYN="Yes",cloudOps*fteMo*E$21,0) | F24: =IF(labourYN="Yes",cloudOps*fteMo*F$21,0) | G24: =IF(labourYN="Yes",cloudOps*fteMo*G$21,0) | H24: =IF(labourYN="Yes",cloudOps*fteMo*H$21,0) | I24: =IF(labourYN="Yes",cloudOps*fteMo*I$21,0) | J24: =IF(labourYN="Yes",cloudOps*fteMo*J$21,0) | ... N24: =IF(labourYN="Yes",cloudOps*fteMo*N$21,0)
A25: Fleet draw kW | C25: =C$16*gpuW/1000*1.25 | D25: =D$16*gpuW/1000*1.25 | E25: =E$16*gpuW/1000*1.25 | F25: =F$16*gpuW/1000*1.25 | G25: =G$16*gpuW/1000*1.25 | H25: =H$16*gpuW/1000*1.25 | I25: =I$16*gpuW/1000*1.25 | J25: =J$16*gpuW/1000*1.25 | ... N25: =N$16*gpuW/1000*1.25
A26: Developer time, open model | C26: =C$5*tasksDay*workdays*MAX(0,mins_o-baseMins)/60*devRate | D26: =D$5*tasksDay*workdays*MAX(0,mins_o-baseMins)/60*devRate | E26: =E$5*tasksDay*workdays*MAX(0,mins_o-baseMins)/60*devRate | F26: =F$5*tasksDay*workdays*MAX(0,mins_o-baseMins)/60*devRate | G26: =G$5*tasksDay*workdays*MAX(0,mins_o-baseMins)/60*devRate | H26: =H$5*tasksDay*workdays*MAX(0,mins_o-baseMins)/60*devRate | I26: =I$5*tasksDay*workdays*MAX(0,mins_o-baseMins)/60*devRate | J26: =J$5*tasksDay*workdays*MAX(0,mins_o-baseMins)/60*devRate | ... N26: =N$5*tasksDay*workdays*MAX(0,mins_o-baseMins)/60*devRate
A27: Developer time, frontier | C27: =C$5*tasksDay*workdays*MAX(0,mins_f-baseMins)/60*devRate | D27: =D$5*tasksDay*workdays*MAX(0,mins_f-baseMins)/60*devRate | E27: =E$5*tasksDay*workdays*MAX(0,mins_f-baseMins)/60*devRate | F27: =F$5*tasksDay*workdays*MAX(0,mins_f-baseMins)/60*devRate | G27: =G$5*tasksDay*workdays*MAX(0,mins_f-baseMins)/60*devRate | H27: =H$5*tasksDay*workdays*MAX(0,mins_f-baseMins)/60*devRate | I27: =I$5*tasksDay*workdays*MAX(0,mins_f-baseMins)/60*devRate | J27: =J$5*tasksDay*workdays*MAX(0,mins_f-baseMins)/60*devRate | ... N27: =N$5*tasksDay*workdays*MAX(0,mins_f-baseMins)/60*devRate
A28: Developer time, hybrid | C28: =C$5*tasksDay*workdays*MAX(0,mins_h-baseMins)/60*devRate | D28: =D$5*tasksDay*workdays*MAX(0,mins_h-baseMins)/60*devRate | E28: =E$5*tasksDay*workdays*MAX(0,mins_h-baseMins)/60*devRate | F28: =F$5*tasksDay*workdays*MAX(0,mins_h-baseMins)/60*devRate | G28: =G$5*tasksDay*workdays*MAX(0,mins_h-baseMins)/60*devRate | H28: =H$5*tasksDay*workdays*MAX(0,mins_h-baseMins)/60*devRate | I28: =I$5*tasksDay*workdays*MAX(0,mins_h-baseMins)/60*devRate | J28: =J$5*tasksDay*workdays*MAX(0,mins_h-baseMins)/60*devRate | ... N28: =N$5*tasksDay*workdays*MAX(0,mins_h-baseMins)/60*devRate
A29: Peak demand, hybrid open tier | C29: =IF(AND(workdays>0,activeHrs>0),C$8*own_h/workdays/(activeHrs*3600)*peak,0) | D29: =IF(AND(workdays>0,activeHrs>0),D$8*own_h/workdays/(activeHrs*3600)*peak,0) | E29: =IF(AND(workdays>0,activeHrs>0),E$8*own_h/workdays/(activeHrs*3600)*peak,0) | F29: =IF(AND(workdays>0,activeHrs>0),F$8*own_h/workdays/(activeHrs*3600)*peak,0) | G29: =IF(AND(workdays>0,activeHrs>0),G$8*own_h/workdays/(activeHrs*3600)*peak,0) | H29: =IF(AND(workdays>0,activeHrs>0),H$8*own_h/workdays/(activeHrs*3600)*peak,0) | I29: =IF(AND(workdays>0,activeHrs>0),I$8*own_h/workdays/(activeHrs*3600)*peak,0) | J29: =IF(AND(workdays>0,activeHrs>0),J$8*own_h/workdays/(activeHrs*3600)*peak,0) | ... N29: =IF(AND(workdays>0,activeHrs>0),N$8*own_h/workdays/(activeHrs*3600)*peak,0)
A30: Hybrid replicas | C30: =IF(C$5=0,0,IF(replicaTps>0,MAX(1,CEILING(C$29/replicaTps,1)),1)) | D30: =IF(D$5=0,0,IF(replicaTps>0,MAX(1,CEILING(D$29/replicaTps,1)),1)) | E30: =IF(E$5=0,0,IF(replicaTps>0,MAX(1,CEILING(E$29/replicaTps,1)),1)) | F30: =IF(F$5=0,0,IF(replicaTps>0,MAX(1,CEILING(F$29/replicaTps,1)),1)) | G30: =IF(G$5=0,0,IF(replicaTps>0,MAX(1,CEILING(G$29/replicaTps,1)),1)) | H30: =IF(H$5=0,0,IF(replicaTps>0,MAX(1,CEILING(H$29/replicaTps,1)),1)) | I30: =IF(I$5=0,0,IF(replicaTps>0,MAX(1,CEILING(I$29/replicaTps,1)),1)) | J30: =IF(J$5=0,0,IF(replicaTps>0,MAX(1,CEILING(J$29/replicaTps,1)),1)) | ... N30: =IF(N$5=0,0,IF(replicaTps>0,MAX(1,CEILING(N$29/replicaTps,1)),1))
A31: Hybrid cards | C31: =C$30*gpusPerReplica | D31: =D$30*gpusPerReplica | E31: =E$30*gpusPerReplica | F31: =F$30*gpusPerReplica | G31: =G$30*gpusPerReplica | H31: =H$30*gpusPerReplica | I31: =I$30*gpusPerReplica | J31: =J$30*gpusPerReplica | ... N31: =N$30*gpusPerReplica
A32: Hybrid hosts | C32: =CEILING(C$31/8,1) | D32: =CEILING(D$31/8,1) | E32: =CEILING(E$31/8,1) | F32: =CEILING(F$31/8,1) | G32: =CEILING(G$31/8,1) | H32: =CEILING(H$31/8,1) | I32: =CEILING(I$31/8,1) | J32: =CEILING(J$31/8,1) | ... N32: =CEILING(N$31/8,1)
A33: Hybrid hardware capital | C33: =C$31*gpuBuy*(1+spares)+C$32*(hostCost+netFabric+installHost) | D33: =D$31*gpuBuy*(1+spares)+D$32*(hostCost+netFabric+installHost) | E33: =E$31*gpuBuy*(1+spares)+E$32*(hostCost+netFabric+installHost) | F33: =F$31*gpuBuy*(1+spares)+F$32*(hostCost+netFabric+installHost) | G33: =G$31*gpuBuy*(1+spares)+G$32*(hostCost+netFabric+installHost) | H33: =H$31*gpuBuy*(1+spares)+H$32*(hostCost+netFabric+installHost) | I33: =I$31*gpuBuy*(1+spares)+I$32*(hostCost+netFabric+installHost) | J33: =J$31*gpuBuy*(1+spares)+J$32*(hostCost+netFabric+installHost) | ... N33: =N$31*gpuBuy*(1+spares)+N$32*(hostCost+netFabric+installHost)
A34: Hybrid, if bought | C34: =C$33/amort+C$31*gpuW/1000*1.25*(pue*730*kwhDc+coloKw)+storMo+C$33*warranty/12+C$20/amort | D34: =D$33/amort+D$31*gpuW/1000*1.25*(pue*730*kwhDc+coloKw)+storMo+D$33*warranty/12+D$20/amort | E34: =E$33/amort+E$31*gpuW/1000*1.25*(pue*730*kwhDc+coloKw)+storMo+E$33*warranty/12+E$20/amort | F34: =F$33/amort+F$31*gpuW/1000*1.25*(pue*730*kwhDc+coloKw)+storMo+F$33*warranty/12+F$20/amort | G34: =G$33/amort+G$31*gpuW/1000*1.25*(pue*730*kwhDc+coloKw)+storMo+G$33*warranty/12+G$20/amort | H34: =H$33/amort+H$31*gpuW/1000*1.25*(pue*730*kwhDc+coloKw)+storMo+H$33*warranty/12+H$20/amort | I34: =I$33/amort+I$31*gpuW/1000*1.25*(pue*730*kwhDc+coloKw)+storMo+I$33*warranty/12+I$20/amort | J34: =J$33/amort+J$31*gpuW/1000*1.25*(pue*730*kwhDc+coloKw)+storMo+J$33*warranty/12+J$20/amort | ... N34: =N$33/amort+N$31*gpuW/1000*1.25*(pue*730*kwhDc+coloKw)+storMo+N$33*warranty/12+N$20/amort
A35: Hybrid, if rented | C35: =C$31*gpuRent*730*rentUtil+storMo+rentSetup/amort | D35: =D$31*gpuRent*730*rentUtil+storMo+rentSetup/amort | E35: =E$31*gpuRent*730*rentUtil+storMo+rentSetup/amort | F35: =F$31*gpuRent*730*rentUtil+storMo+rentSetup/amort | G35: =G$31*gpuRent*730*rentUtil+storMo+rentSetup/amort | H35: =H$31*gpuRent*730*rentUtil+storMo+rentSetup/amort | I35: =I$31*gpuRent*730*rentUtil+storMo+rentSetup/amort | J35: =J$31*gpuRent*730*rentUtil+storMo+rentSetup/amort | ... N35: =N$31*gpuRent*730*rentUtil+storMo+rentSetup/amort
A36: Cheaper to buy the hybrid fleet? | C36: =IF(C$34<=C$35,"Yes","No") | D36: =IF(D$34<=D$35,"Yes","No") | E36: =IF(E$34<=E$35,"Yes","No") | F36: =IF(F$34<=F$35,"Yes","No") | G36: =IF(G$34<=G$35,"Yes","No") | H36: =IF(H$34<=H$35,"Yes","No") | I36: =IF(I$34<=I$35,"Yes","No") | J36: =IF(J$34<=J$35,"Yes","No") | ... N36: =IF(N$34<=N$35,"Yes","No")
A38: MONTHLY COST OF EVERY ROUTE, AT EVERY TEAM SIZE
A39: Route | C39: 1 | D39: 2 | E39: 5 | F39: 10 | G39: 25 | H39: 50 | I39: 100 | J39: 200 | K39: 350 | L39: 500 | M39: 750 | N39: 1000
A40: Local model on laptops | C40: =C$5*lapUplift/amort+C$5*lapWatts/1000*codeHrs*workdays*kwhOffice+IF(labourYN="Yes",C$5*lapSupport/12*itRate,0)+C$26 | D40: =D$5*lapUplift/amort+D$5*lapWatts/1000*codeHrs*workdays*kwhOffice+IF(labourYN="Yes",D$5*lapSupport/12*itRate,0)+D$26 | E40: =E$5*lapUplift/amort+E$5*lapWatts/1000*codeHrs*workdays*kwhOffice+IF(labourYN="Yes",E$5*lapSupport/12*itRate,0)+E$26 | F40: =F$5*lapUplift/amort+F$5*lapWatts/1000*codeHrs*workdays*kwhOffice+IF(labourYN="Yes",F$5*lapSupport/12*itRate,0)+F$26 | G40: =G$5*lapUplift/amort+G$5*lapWatts/1000*codeHrs*workdays*kwhOffice+IF(labourYN="Yes",G$5*lapSupport/12*itRate,0)+G$26 | H40: =H$5*lapUplift/amort+H$5*lapWatts/1000*codeHrs*workdays*kwhOffice+IF(labourYN="Yes",H$5*lapSupport/12*itRate,0)+H$26 | I40: =I$5*lapUplift/amort+I$5*lapWatts/1000*codeHrs*workdays*kwhOffice+IF(labourYN="Yes",I$5*lapSupport/12*itRate,0)+I$26 | J40: =J$5*lapUplift/amort+J$5*lapWatts/1000*codeHrs*workdays*kwhOffice+IF(labourYN="Yes",J$5*lapSupport/12*itRate,0)+J$26 | ... N40: =N$5*lapUplift/amort+N$5*lapWatts/1000*codeHrs*workdays*kwhOffice+IF(labourYN="Yes",N$5*lapSupport/12*itRate,0)+N$26
A41: GPUs you buy | C41: =C$19/amort+C$25*(pue*730*kwhDc+coloKw)+storMo+C$19*warranty/12+C$22+C$23+C$20/amort+C$26 | D41: =D$19/amort+D$25*(pue*730*kwhDc+coloKw)+storMo+D$19*warranty/12+D$22+D$23+D$20/amort+D$26 | E41: =E$19/amort+E$25*(pue*730*kwhDc+coloKw)+storMo+E$19*warranty/12+E$22+E$23+E$20/amort+E$26 | F41: =F$19/amort+F$25*(pue*730*kwhDc+coloKw)+storMo+F$19*warranty/12+F$22+F$23+F$20/amort+F$26 | G41: =G$19/amort+G$25*(pue*730*kwhDc+coloKw)+storMo+G$19*warranty/12+G$22+G$23+G$20/amort+G$26 | H41: =H$19/amort+H$25*(pue*730*kwhDc+coloKw)+storMo+H$19*warranty/12+H$22+H$23+H$20/amort+H$26 | I41: =I$19/amort+I$25*(pue*730*kwhDc+coloKw)+storMo+I$19*warranty/12+I$22+I$23+I$20/amort+I$26 | J41: =J$19/amort+J$25*(pue*730*kwhDc+coloKw)+storMo+J$19*warranty/12+J$22+J$23+J$20/amort+J$26 | ... N41: =N$19/amort+N$25*(pue*730*kwhDc+coloKw)+storMo+N$19*warranty/12+N$22+N$23+N$20/amort+N$26
A42: GPUs you rent by the hour | C42: =C$16*gpuRent*730*rentUtil+storMo+C$22+C$23+rentSetup/amort+C$26 | D42: =D$16*gpuRent*730*rentUtil+storMo+D$22+D$23+rentSetup/amort+D$26 | E42: =E$16*gpuRent*730*rentUtil+storMo+E$22+E$23+rentSetup/amort+E$26 | F42: =F$16*gpuRent*730*rentUtil+storMo+F$22+F$23+rentSetup/amort+F$26 | G42: =G$16*gpuRent*730*rentUtil+storMo+G$22+G$23+rentSetup/amort+G$26 | H42: =H$16*gpuRent*730*rentUtil+storMo+H$22+H$23+rentSetup/amort+H$26 | I42: =I$16*gpuRent*730*rentUtil+storMo+I$22+I$23+rentSetup/amort+I$26 | J42: =J$16*gpuRent*730*rentUtil+storMo+J$22+J$23+rentSetup/amort+J$26 | ... N42: =N$16*gpuRent*730*rentUtil+storMo+N$22+N$23+rentSetup/amort+N$26
A43: Open model, hosted by someone else | C43: =C$22+(C$11*tm_o/1000000*orIn+C$10*tm_o/1000000*orCache+C$8*tm_o/1000000*orOut)*disc*(1+orFee)+C$26 | D43: =D$22+(D$11*tm_o/1000000*orIn+D$10*tm_o/1000000*orCache+D$8*tm_o/1000000*orOut)*disc*(1+orFee)+D$26 | E43: =E$22+(E$11*tm_o/1000000*orIn+E$10*tm_o/1000000*orCache+E$8*tm_o/1000000*orOut)*disc*(1+orFee)+E$26 | F43: =F$22+(F$11*tm_o/1000000*orIn+F$10*tm_o/1000000*orCache+F$8*tm_o/1000000*orOut)*disc*(1+orFee)+F$26 | G43: =G$22+(G$11*tm_o/1000000*orIn+G$10*tm_o/1000000*orCache+G$8*tm_o/1000000*orOut)*disc*(1+orFee)+G$26 | H43: =H$22+(H$11*tm_o/1000000*orIn+H$10*tm_o/1000000*orCache+H$8*tm_o/1000000*orOut)*disc*(1+orFee)+H$26 | I43: =I$22+(I$11*tm_o/1000000*orIn+I$10*tm_o/1000000*orCache+I$8*tm_o/1000000*orOut)*disc*(1+orFee)+I$26 | J43: =J$22+(J$11*tm_o/1000000*orIn+J$10*tm_o/1000000*orCache+J$8*tm_o/1000000*orOut)*disc*(1+orFee)+J$26 | ... N43: =N$22+(N$11*tm_o/1000000*orIn+N$10*tm_o/1000000*orCache+N$8*tm_o/1000000*orOut)*disc*(1+orFee)+N$26
A44: AWS Bedrock | C44: =C$22+C$24+(C$11*1/1000000*bedIn+C$10*1/1000000*bedCache+C$8*1/1000000*bedOut)*disc+C$27 | D44: =D$22+D$24+(D$11*1/1000000*bedIn+D$10*1/1000000*bedCache+D$8*1/1000000*bedOut)*disc+D$27 | E44: =E$22+E$24+(E$11*1/1000000*bedIn+E$10*1/1000000*bedCache+E$8*1/1000000*bedOut)*disc+E$27 | F44: =F$22+F$24+(F$11*1/1000000*bedIn+F$10*1/1000000*bedCache+F$8*1/1000000*bedOut)*disc+F$27 | G44: =G$22+G$24+(G$11*1/1000000*bedIn+G$10*1/1000000*bedCache+G$8*1/1000000*bedOut)*disc+G$27 | H44: =H$22+H$24+(H$11*1/1000000*bedIn+H$10*1/1000000*bedCache+H$8*1/1000000*bedOut)*disc+H$27 | I44: =I$22+I$24+(I$11*1/1000000*bedIn+I$10*1/1000000*bedCache+I$8*1/1000000*bedOut)*disc+I$27 | J44: =J$22+J$24+(J$11*1/1000000*bedIn+J$10*1/1000000*bedCache+J$8*1/1000000*bedOut)*disc+J$27 | ... N44: =N$22+N$24+(N$11*1/1000000*bedIn+N$10*1/1000000*bedCache+N$8*1/1000000*bedOut)*disc+N$27
A45: Azure OpenAI | C45: =C$22+C$24+(C$11*1/1000000*azIn+C$10*1/1000000*azCache+C$8*1/1000000*azOut)*disc+C$27 | D45: =D$22+D$24+(D$11*1/1000000*azIn+D$10*1/1000000*azCache+D$8*1/1000000*azOut)*disc+D$27 | E45: =E$22+E$24+(E$11*1/1000000*azIn+E$10*1/1000000*azCache+E$8*1/1000000*azOut)*disc+E$27 | F45: =F$22+F$24+(F$11*1/1000000*azIn+F$10*1/1000000*azCache+F$8*1/1000000*azOut)*disc+F$27 | G45: =G$22+G$24+(G$11*1/1000000*azIn+G$10*1/1000000*azCache+G$8*1/1000000*azOut)*disc+G$27 | H45: =H$22+H$24+(H$11*1/1000000*azIn+H$10*1/1000000*azCache+H$8*1/1000000*azOut)*disc+H$27 | I45: =I$22+I$24+(I$11*1/1000000*azIn+I$10*1/1000000*azCache+I$8*1/1000000*azOut)*disc+I$27 | J45: =J$22+J$24+(J$11*1/1000000*azIn+J$10*1/1000000*azCache+J$8*1/1000000*azOut)*disc+J$27 | ... N45: =N$22+N$24+(N$11*1/1000000*azIn+N$10*1/1000000*azCache+N$8*1/1000000*azOut)*disc+N$27
A46: Anthropic API | C46: =C$22+(C$11*1/1000000*anIn+C$10*1/1000000*anCache+C$8*1/1000000*anOut)*disc+C$27 | D46: =D$22+(D$11*1/1000000*anIn+D$10*1/1000000*anCache+D$8*1/1000000*anOut)*disc+D$27 | E46: =E$22+(E$11*1/1000000*anIn+E$10*1/1000000*anCache+E$8*1/1000000*anOut)*disc+E$27 | F46: =F$22+(F$11*1/1000000*anIn+F$10*1/1000000*anCache+F$8*1/1000000*anOut)*disc+F$27 | G46: =G$22+(G$11*1/1000000*anIn+G$10*1/1000000*anCache+G$8*1/1000000*anOut)*disc+G$27 | H46: =H$22+(H$11*1/1000000*anIn+H$10*1/1000000*anCache+H$8*1/1000000*anOut)*disc+H$27 | I46: =I$22+(I$11*1/1000000*anIn+I$10*1/1000000*anCache+I$8*1/1000000*anOut)*disc+I$27 | J46: =J$22+(J$11*1/1000000*anIn+J$10*1/1000000*anCache+J$8*1/1000000*anOut)*disc+J$27 | ... N46: =N$22+(N$11*1/1000000*anIn+N$10*1/1000000*anCache+N$8*1/1000000*anOut)*disc+N$27
A47: OpenAI API | C47: =C$22+(C$11*1/1000000*oaIn+C$10*1/1000000*oaCache+C$8*1/1000000*oaOut)*disc+C$27 | D47: =D$22+(D$11*1/1000000*oaIn+D$10*1/1000000*oaCache+D$8*1/1000000*oaOut)*disc+D$27 | E47: =E$22+(E$11*1/1000000*oaIn+E$10*1/1000000*oaCache+E$8*1/1000000*oaOut)*disc+E$27 | F47: =F$22+(F$11*1/1000000*oaIn+F$10*1/1000000*oaCache+F$8*1/1000000*oaOut)*disc+F$27 | G47: =G$22+(G$11*1/1000000*oaIn+G$10*1/1000000*oaCache+G$8*1/1000000*oaOut)*disc+G$27 | H47: =H$22+(H$11*1/1000000*oaIn+H$10*1/1000000*oaCache+H$8*1/1000000*oaOut)*disc+H$27 | I47: =I$22+(I$11*1/1000000*oaIn+I$10*1/1000000*oaCache+I$8*1/1000000*oaOut)*disc+I$27 | J47: =J$22+(J$11*1/1000000*oaIn+J$10*1/1000000*oaCache+J$8*1/1000000*oaOut)*disc+J$27 | ... N47: =N$22+(N$11*1/1000000*oaIn+N$10*1/1000000*oaCache+N$8*1/1000000*oaOut)*disc+N$27
A48: Open model, frontier fallback | C48: =IF(C$36="Yes",C$34,C$35)+C$22+C$23+(C$11*api_h/1000000*anIn+C$10*api_h/1000000*anCache+C$8*api_h/1000000*anOut)*disc+C$28 | D48: =IF(D$36="Yes",D$34,D$35)+D$22+D$23+(D$11*api_h/1000000*anIn+D$10*api_h/1000000*anCache+D$8*api_h/1000000*anOut)*disc+D$28 | E48: =IF(E$36="Yes",E$34,E$35)+E$22+E$23+(E$11*api_h/1000000*anIn+E$10*api_h/1000000*anCache+E$8*api_h/1000000*anOut)*disc+E$28 | F48: =IF(F$36="Yes",F$34,F$35)+F$22+F$23+(F$11*api_h/1000000*anIn+F$10*api_h/1000000*anCache+F$8*api_h/1000000*anOut)*disc+F$28 | G48: =IF(G$36="Yes",G$34,G$35)+G$22+G$23+(G$11*api_h/1000000*anIn+G$10*api_h/1000000*anCache+G$8*api_h/1000000*anOut)*disc+G$28 | H48: =IF(H$36="Yes",H$34,H$35)+H$22+H$23+(H$11*api_h/1000000*anIn+H$10*api_h/1000000*anCache+H$8*api_h/1000000*anOut)*disc+H$28 | I48: =IF(I$36="Yes",I$34,I$35)+I$22+I$23+(I$11*api_h/1000000*anIn+I$10*api_h/1000000*anCache+I$8*api_h/1000000*anOut)*disc+I$28 | J48: =IF(J$36="Yes",J$34,J$35)+J$22+J$23+(J$11*api_h/1000000*anIn+J$10*api_h/1000000*anCache+J$8*api_h/1000000*anOut)*disc+J$28 | ... N48: =IF(N$36="Yes",N$34,N$35)+N$22+N$23+(N$11*api_h/1000000*anIn+N$10*api_h/1000000*anCache+N$8*api_h/1000000*anOut)*disc+N$28
A49: Flat per-seat plans | C49: =C$22+C$5*(seat+IF(ownsBase="Yes",0,seatBase))+C$27 | D49: =D$22+D$5*(seat+IF(ownsBase="Yes",0,seatBase))+D$27 | E49: =E$22+E$5*(seat+IF(ownsBase="Yes",0,seatBase))+E$27 | F49: =F$22+F$5*(seat+IF(ownsBase="Yes",0,seatBase))+F$27 | G49: =G$22+G$5*(seat+IF(ownsBase="Yes",0,seatBase))+G$27 | H49: =H$22+H$5*(seat+IF(ownsBase="Yes",0,seatBase))+H$27 | I49: =I$22+I$5*(seat+IF(ownsBase="Yes",0,seatBase))+I$27 | J49: =J$22+J$5*(seat+IF(ownsBase="Yes",0,seatBase))+J$27 | ... N49: =N$22+N$5*(seat+IF(ownsBase="Yes",0,seatBase))+N$27
A51: WHERE IT CROSSES
A52: Full-term cash, buying the fleet | C52: =(C$19+C$20)+(C$41-C$19/amort-C$26)*horizon | D52: =(D$19+D$20)+(D$41-D$19/amort-D$26)*horizon | E52: =(E$19+E$20)+(E$41-E$19/amort-E$26)*horizon | F52: =(F$19+F$20)+(F$41-F$19/amort-F$26)*horizon | G52: =(G$19+G$20)+(G$41-G$19/amort-G$26)*horizon | H52: =(H$19+H$20)+(H$41-H$19/amort-H$26)*horizon | I52: =(I$19+I$20)+(I$41-I$19/amort-I$26)*horizon | J52: =(J$19+J$20)+(J$41-J$19/amort-J$26)*horizon | ... N52: =(N$19+N$20)+(N$41-N$19/amort-N$26)*horizon
A53: Full-term cash, renting the fleet | C53: =rentSetup+(C$42-C$26)*horizon | D53: =rentSetup+(D$42-D$26)*horizon | E53: =rentSetup+(E$42-E$26)*horizon | F53: =rentSetup+(F$42-F$26)*horizon | G53: =rentSetup+(G$42-G$26)*horizon | H53: =rentSetup+(H$42-H$26)*horizon | I53: =rentSetup+(I$42-I$26)*horizon | J53: =rentSetup+(J$42-J$26)*horizon | ... N53: =rentSetup+(N$42-N$26)*horizon
A54: Full-term cash, hybrid | C54: =IF(C$36="Yes",C$33+C$20,rentSetup)+(C$48-IF(C$36="Yes",C$33/amort,0)-C$28)*horizon | D54: =IF(D$36="Yes",D$33+D$20,rentSetup)+(D$48-IF(D$36="Yes",D$33/amort,0)-D$28)*horizon | E54: =IF(E$36="Yes",E$33+E$20,rentSetup)+(E$48-IF(E$36="Yes",E$33/amort,0)-E$28)*horizon | F54: =IF(F$36="Yes",F$33+F$20,rentSetup)+(F$48-IF(F$36="Yes",F$33/amort,0)-F$28)*horizon | G54: =IF(G$36="Yes",G$33+G$20,rentSetup)+(G$48-IF(G$36="Yes",G$33/amort,0)-G$28)*horizon | H54: =IF(H$36="Yes",H$33+H$20,rentSetup)+(H$48-IF(H$36="Yes",H$33/amort,0)-H$28)*horizon | I54: =IF(I$36="Yes",I$33+I$20,rentSetup)+(I$48-IF(I$36="Yes",I$33/amort,0)-I$28)*horizon | J54: =IF(J$36="Yes",J$33+J$20,rentSetup)+(J$48-IF(J$36="Yes",J$33/amort,0)-J$28)*horizon | ... N54: =IF(N$36="Yes",N$33+N$20,rentSetup)+(N$48-IF(N$36="Yes",N$33/amort,0)-N$28)*horizon
A55: Full-term cash, cheapest hosted | B55: serverless, the clouds, the labs, seats and the hybrid | C55: =MIN((C$43-C$26)*horizon,(C$44-C$27)*horizon,(C$45-C$27)*horizon,(C$46-C$27)*horizon,(C$47-C$27)*horizon,(C$49-C$27)*horizon,C$54) | D55: =MIN((D$43-D$26)*horizon,(D$44-D$27)*horizon,(D$45-D$27)*horizon,(D$46-D$27)*horizon,(D$47-D$27)*horizon,(D$49-D$27)*horizon,D$54) | E55: =MIN((E$43-E$26)*horizon,(E$44-E$27)*horizon,(E$45-E$27)*horizon,(E$46-E$27)*horizon,(E$47-E$27)*horizon,(E$49-E$27)*horizon,E$54) | F55: =MIN((F$43-F$26)*horizon,(F$44-F$27)*horizon,(F$45-F$27)*horizon,(F$46-F$27)*horizon,(F$47-F$27)*horizon,(F$49-F$27)*horizon,F$54) | G55: =MIN((G$43-G$26)*horizon,(G$44-G$27)*horizon,(G$45-G$27)*horizon,(G$46-G$27)*horizon,(G$47-G$27)*horizon,(G$49-G$27)*horizon,G$54) | H55: =MIN((H$43-H$26)*horizon,(H$44-H$27)*horizon,(H$45-H$27)*horizon,(H$46-H$27)*horizon,(H$47-H$27)*horizon,(H$49-H$27)*horizon,H$54) | I55: =MIN((I$43-I$26)*horizon,(I$44-I$27)*horizon,(I$45-I$27)*horizon,(I$46-I$27)*horizon,(I$47-I$27)*horizon,(I$49-I$27)*horizon,I$54) | J55: =MIN((J$43-J$26)*horizon,(J$44-J$27)*horizon,(J$45-J$27)*horizon,(J$46-J$27)*horizon,(J$47-J$27)*horizon,(J$49-J$27)*horizon,J$54) | ... N55: =MIN((N$43-N$26)*horizon,(N$44-N$27)*horizon,(N$45-N$27)*horizon,(N$46-N$27)*horizon,(N$47-N$27)*horizon,(N$49-N$27)*horizon,N$54)
A56: Full-term cash, cheapest fleet you own | B56: buying or renting accelerators - laptops are a different question | C56: =MIN(C$52,C$53) | D56: =MIN(D$52,D$53) | E56: =MIN(E$52,E$53) | F56: =MIN(F$52,F$53) | G56: =MIN(G$52,G$53) | H56: =MIN(H$52,H$53) | I56: =MIN(I$52,I$53) | J56: =MIN(J$52,J$53) | ... N56: =MIN(N$52,N$53)
A57: Does owning win here? | C57: =IF(C$56<C$55,C$5,"") | D57: =IF(D$56<D$55,D$5,"") | E57: =IF(E$56<E$55,E$5,"") | F57: =IF(F$56<F$55,F$5,"") | G57: =IF(G$56<G$55,G$5,"") | H57: =IF(H$56<H$55,H$5,"") | I57: =IF(I$56<I$55,I$5,"") | J57: =IF(J$56<J$55,J$5,"") | ... N57: =IF(N$56<N$55,N$5,"")
A58: Cheapest route | C58: =INDEX(cat_routes,MATCH(MIN(C$40:C$49),C$40:C$49,0)) | D58: =INDEX(cat_routes,MATCH(MIN(D$40:D$49),D$40:D$49,0)) | E58: =INDEX(cat_routes,MATCH(MIN(E$40:E$49),E$40:E$49,0)) | F58: =INDEX(cat_routes,MATCH(MIN(F$40:F$49),F$40:F$49,0)) | G58: =INDEX(cat_routes,MATCH(MIN(G$40:G$49),G$40:G$49,0)) | H58: =INDEX(cat_routes,MATCH(MIN(H$40:H$49),H$40:H$49,0)) | I58: =INDEX(cat_routes,MATCH(MIN(I$40:I$49),I$40:I$49,0)) | J58: =INDEX(cat_routes,MATCH(MIN(J$40:J$49),J$40:J$49,0)) | ... N58: =INDEX(cat_routes,MATCH(MIN(N$40:N$49),N$40:N$49,0))
A59: Per developer, per month | C59: =IF(C$5>0,MIN(C$40:C$49)/C$5,0) | D59: =IF(D$5>0,MIN(D$40:D$49)/D$5,0) | E59: =IF(E$5>0,MIN(E$40:E$49)/E$5,0) | F59: =IF(F$5>0,MIN(F$40:F$49)/F$5,0) | G59: =IF(G$5>0,MIN(G$40:G$49)/G$5,0) | H59: =IF(H$5>0,MIN(H$40:H$49)/H$5,0) | I59: =IF(I$5>0,MIN(I$40:I$49)/I$5,0) | J59: =IF(J$5>0,MIN(J$40:J$49)/J$5,0) | ... N59: =IF(N$5>0,MIN(N$40:N$49)/N$5,0)
A61: Owning accelerators first wins at | B61: developers | C61: =IFERROR(MIN(C$57:N$57),0)
A62: Zero means owning never wins inside the sizes above. Both sides are full-term cash with the developer-time penalty stripped out, so the comparison is about infrastructure rather than about model quality - the fair fight. Put the penalty back and owning has to win by that much more.

Sheet Workings
A1: Workings
A2: Every intermediate the Answer sheet stands on. Nothing here is an input - it is all formulas over the Inputs tab, laid out so each step can be checked by hand.
A4: 1. TOKEN VOLUMES FOR THE MONTH
A5: Input tokens | B5: =devs*inTok*1000000*workdays
A6: Output tokens | B6: =devs*outTok*1000*workdays
A7: Input served from cache | B7: =m_inTok*MIN(1,cacheShare)
A8: Fresh input | B8: =m_inTok-m_cached
A9: Accepted tasks | B9: =devs*tasksDay*workdays
A10: Developer hours in the tool | B10: =devs*codeHrs*workdays
A11: Loaded engineer, per month | B11: =fteCost/12
A12: Loaded engineer, per hour | B12: =fteCost/2080
A13: Metered-token discount factor | B13: =MAX(0,1-apiDiscount)
A14: One session, output tok/s | B14: =IF(codeHrs>0,outTok*1000/(codeHrs*3600),0) | C14: the rate one developer pulls while working
A15: Live sessions at once | B15: =devs*sessConc
A17: 2. THE FAILURE FUNNEL - FIRST PASS, REPAIR PASSES, AND WHAT IS NEVER SOLVED
A18: Attempts are spent on the hopeless share too, which is exactly why retry budgets cost money. A repair pass is worse than the first because the easy wins are gone.
A19: Pass | B19: Frontier pool in | C19: attempts | D19: solved | E19: pool out | F19: Open pool in | G19: attempts | H19: solved | I19: pool out
A20: First pass | B20: =1 | C20: =1 | D20: =B20*acceptFrontier | E20: =B20-D20 | F20: =1 | G20: =1 | H20: =F20*acceptOpen | I20: =F20-H20
A21: Repair 1 | B21: =E20 | C21: =IF(AND(1<=maxRetries,E20>0.000000001),B21,0) | D21: =IF(AND(1<=maxRetries,E20>0.000000001),MAX(0,B21-hardFrontier)*repairFrontier,0) | E21: =B21-D21 | F21: =I20 | G21: =IF(AND(1<=maxRetries,I20>0.000000001),F21,0) | H21: =IF(AND(1<=maxRetries,I20>0.000000001),MAX(0,F21-hardOpen)*repairOpen,0) | I21: =F21-H21
A22: Repair 2 | B22: =E21 | C22: =IF(AND(2<=maxRetries,E21>0.000000001),B22,0) | D22: =IF(AND(2<=maxRetries,E21>0.000000001),MAX(0,B22-hardFrontier)*repairFrontier,0) | E22: =B22-D22 | F22: =I21 | G22: =IF(AND(2<=maxRetries,I21>0.000000001),F22,0) | H22: =IF(AND(2<=maxRetries,I21>0.000000001),MAX(0,F22-hardOpen)*repairOpen,0) | I22: =F22-H22
A23: Repair 3 | B23: =E22 | C23: =IF(AND(3<=maxRetries,E22>0.000000001),B23,0) | D23: =IF(AND(3<=maxRetries,E22>0.000000001),MAX(0,B23-hardFrontier)*repairFrontier,0) | E23: =B23-D23 | F23: =I22 | G23: =IF(AND(3<=maxRetries,I22>0.000000001),F23,0) | H23: =IF(AND(3<=maxRetries,I22>0.000000001),MAX(0,F23-hardOpen)*repairOpen,0) | I23: =F23-H23
A24: Repair 4 | B24: =E23 | C24: =IF(AND(4<=maxRetries,E23>0.000000001),B24,0) | D24: =IF(AND(4<=maxRetries,E23>0.000000001),MAX(0,B24-hardFrontier)*repairFrontier,0) | E24: =B24-D24 | F24: =I23 | G24: =IF(AND(4<=maxRetries,I23>0.000000001),F24,0) | H24: =IF(AND(4<=maxRetries,I23>0.000000001),MAX(0,F24-hardOpen)*repairOpen,0) | I24: =F24-H24
A25: Repair 5 | B25: =E24 | C25: =IF(AND(5<=maxRetries,E24>0.000000001),B25,0) | D25: =IF(AND(5<=maxRetries,E24>0.000000001),MAX(0,B25-hardFrontier)*repairFrontier,0) | E25: =B25-D25 | F25: =I24 | G25: =IF(AND(5<=maxRetries,I24>0.000000001),F25,0) | H25: =IF(AND(5<=maxRetries,I24>0.000000001),MAX(0,F25-hardOpen)*repairOpen,0) | I25: =F25-H25
A26: Totals per unit of work started | C26: =SUM(C20:C25) | D26: =SUM(D20:D25) | E26: =E25 | G26: =SUM(G20:G25) | H26: =SUM(H20:H25) | I26: =I25
A28: 3. HYBRID - THE OPEN MODEL TRIES FIRST, THE FRONTIER TAKES WHAT IS LEFT
A29: Escalated to the frontier | B29: =O_unres
A30: Accepted overall | B30: =O_acc+H_esc*F_acc
A31: Still unresolved | B31: =H_esc*F_unres
A32: Attempts on the open tier | B32: =O_att
A33: Attempts on the frontier tier | B33: =H_esc*F_att
A35: 4. EFFECTIVENESS PER STRATEGY, AGAINST THE FRONTIER YARDSTICK
A36: Strategy | B36: Attempts / accepted task | C36: on open tier | D36: on frontier tier | E36: Unfinished / accepted | F36: Token volume vs frontier | G36: own share | H36: API share | I36: Developer min / task | J36: Developer time charged $/mo
A37: Frontier only | B37: =F_att/F_acc | C37: =0 | D37: =F_att/F_acc | E37: =F_unres/F_acc | F37: =IF($B$37>0,B37/$B$37,1) | G37: =IF($B$37>0,C37/$B$37,0) | H37: =IF($B$37>0,D37/$B$37,0) | I37: =B37*minPerAttempt+IF(countFallback="Yes",E37*minPerHumanTask,0) | J37: =devs*tasksDay*workdays*MAX(0,I37-baseMins)/60*devRate
A38: Open model only | B38: =O_att/O_acc | C38: =O_att/O_acc | D38: =0 | E38: =O_unres/O_acc | F38: =IF($B$37>0,B38/$B$37,1) | G38: =IF($B$37>0,C38/$B$37,0) | H38: =IF($B$37>0,D38/$B$37,0) | I38: =B38*minPerAttempt+IF(countFallback="Yes",E38*minPerHumanTask,0) | J38: =devs*tasksDay*workdays*MAX(0,I38-baseMins)/60*devRate
A39: Open first, frontier fallback | B39: =(H_openAtt+H_frontAtt)/H_acc | C39: =H_openAtt/H_acc | D39: =H_frontAtt/H_acc | E39: =H_unres/H_acc | F39: =IF($B$37>0,B39/$B$37,1) | G39: =IF($B$37>0,C39/$B$37,0) | H39: =IF($B$37>0,D39/$B$37,0) | I39: =B39*minPerAttempt+IF(countFallback="Yes",E39*minPerHumanTask,0) | J39: =devs*tasksDay*workdays*MAX(0,I39-baseMins)/60*devRate
A40: Fewest minutes of the three (the baseline) | I40: =MIN($I$37:$I$39)
A41: Only the DIFFERENTIAL developer time is charged, against whichever strategy needs the fewest minutes. Ordinary review labour exists on every route and is not this model's to count.
A44: 5. SIZING THE FLEET THE OPEN MODEL WOULD NEED
A45: Total parameters | B45: =INDEX(tbl_models,MATCH(sel_model,cat_models,0),2) | C45: B
A46: Active parameters | B46: =INDEX(tbl_models,MATCH(sel_model,cat_models,0),3) | C46: B per token
A47: KV per k token | B47: =INDEX(tbl_models,MATCH(sel_model,cat_models,0),4) | C47: MB
A48: Bytes per parameter | B48: =INDEX(tbl_quants,MATCH(sel_quant,cat_quants,0),2)
A49: KV factor | B49: =INDEX(tbl_quants,MATCH(sel_quant,cat_quants,0),3)
A50: Weights in memory | B50: =m_total*q_bytes | C50: GB
A51: KV cache | B51: =batch*ctxK*1000*m_kv*q_kv/1024 | C51: GB
A52: Activation and fragmentation overhead | B52: =weightsGb*0.15 | C52: GB, 15%
A53: Memory per replica | B53: =weightsGb+kvGb+ovGb | C53: GB
A54: Cards the memory alone needs | B54: =MAX(1,CEILING(vramNeed/MAX(1,gpuVram),1))
A55: Cards per replica | B55: =IF(rawCards<=nodeSize,MIN(nodeSize,POWER(2,CEILING(LOG(rawCards,2)-0.0000001,1))),CEILING(rawCards/nodeSize,1)*nodeSize) | C55: inside a node, a power of two; past it, whole nodes
A56: Nodes per replica | B56: =CEILING(gpusPerReplica/nodeSize,1)
A57: Interconnect efficiency | B57: =IF(nodesPerReplica>1,MAX(0.05,1-multiNodeLoss),1)
A58: Bytes read per token | B58: =m_active*q_bytes | C58: GB
A59: One stream | B59: =MIN(gpusPerReplica*MAX(1,gpuBw)*linkEff/bytesPerTok*bwEff,streamCap) | C59: tok/s
A60: One replica | B60: =perStream*MIN(batch,32) | C60: tok/s
A61: Peak demand, open model | B61: =IF(AND(workdays>0,activeHrs>0),m_outTok*tm_o/workdays/(activeHrs*3600)*peak,0) | C61: tok/s in the busy hour
A62: Replicas needed | B62: =IF(devs=0,0,IF(replicaTps>0,MAX(1,CEILING(peakTps/replicaTps,1)),1))
A63: Cards in the fleet | B63: =replicas*gpusPerReplica
A64: Sustained fleet throughput | B64: =replicas*replicaTps | C64: tok/s
A65: Time to first token | B65: =IF(gpusPerReplica*gpuTf*linkEff*bwEff>0,2*m_active*ctxK*1000/(gpusPerReplica*gpuTf*1000*linkEff*bwEff),0) | C65: s, cold prefill with nothing cached
A66: Checkpoint storage | B66: =(m_total*2+m_total*q_bytes)*MAX(1,ckpts) | C66: GB
A67: Fits a laptop | B67: =IF(weightsGb+ovGb+4<=lapRam,"Yes","No")
A68: One laptop | B68: =lapBw/MAX(0.001,bytesPerTok)*bwEff | C68: tok/s
A70: 6. THE HYBRID'S OWN FLEET - IT SERVES THE OPEN TIER ONLY
A71: Peak demand, open tier only | B71: =IF(AND(workdays>0,activeHrs>0),m_outTok*own_h/workdays/(activeHrs*3600)*peak,0) | C71: tok/s
A72: Replicas needed | B72: =IF(devs=0,0,IF(replicaTps>0,MAX(1,CEILING(peakTpsH/replicaTps,1)),1))
A73: Cards in the hybrid fleet | B73: =replicasH*gpusPerReplica
A74: Hosts | B74: =CEILING(gpusH/8,1)
A75: Sustained hybrid fleet throughput | B75: =replicasH*replicaTps | C75: tok/s
A77: 7. WHAT THE IRON AND THE PEOPLE COST
A78: Hosts | B78: =CEILING(gpus/8,1) | C78: eight cards to a host
A79: Cards | B79: =gpus*gpuBuy
A80: Spare cards held | B80: =cardsCost*spares
A81: Hosts, NICs and fabric | B81: =hosts*hostCost
A82: Fabric, optics and cabling | B82: =hosts*netFabric
A83: Rack, PDU and smart hands | B83: =hosts*installHost
A84: Hardware capital | B84: =cardsCost+sparesCost+chassisCost+fabricCost+installCost
A85: Setup hours | B85: =setupArch+hosts*setupRack+setupStack+setupEval+setupSec
A86: Setup labour | B86: =IF(labourYN="Yes",setupHours*engHr,0) | C86: one-off, and it does NOT scale down with the team
A87: Day-one cheque if you buy | B87: =hwCapex+setupLabour
A88: Hardware support | B88: =hwCapex*warranty/12 | C88: per month
A89: Bring-up if you rent instead | B89: =IF(labourYN="Yes",(setupStack+setupEval+setupSec+setupArch/2)*engHr,0) | C89: no rack, but still a serving stack, an evaluation and a security review
A90: Staffing ramp | B90: =IF(platformAt>soloAt,MIN(1,MAX(0,(devs-soloAt)/(platformAt-soloAt))),IF(devs>soloAt,1,0)) | C90: nobody is employed to run this below the small-team threshold; full strength at platformAt
A91: Baseline AI platform team | B91: =IF(AND(labourYN="Yes",ownsPlatform="No"),platformFte*fteMo*teamRamp,0) | C91: every centralised route pays this
A92: Fleet admin | B92: =IF(labourYN="Yes",adminFte*fteMo*teamRamp,0)
A93: Cloud plumbing | B93: =IF(labourYN="Yes",cloudOps*fteMo*teamRamp,0)
A94: Fleet draw | B94: =gpus*gpuW/1000*1.25 | C94: kW, +25% for host, NIC and fans
A95: Storage | B95: =storageGb*storGb | C95: per month
A97: 8. THE HYBRID: BUY ITS FLEET, OR RENT IT?
A98: Hybrid fleet draw | B98: =gpusH*gpuW/1000*1.25 | C98: kW
A99: Hybrid hardware capital | B99: =gpusH*gpuBuy*(1+spares)+hostsH*(hostCost+netFabric+installHost) | C99: its OWN fleet, not the standalone one
A100: Written down per month | B100: =hHwCapex/amort
A101: Power, rack, storage and support | B101: =hKw*pue*730*kwhDc+hKw*coloKw+storMo+hHwCapex*warranty/12
A102: Rent the same fleet instead | B102: =gpusH*gpuRent*730*rentUtil
A103: Total if bought | B103: =hybridFleetCapex+hybridFleetPower+setupLabour/amort
A104: Total if rented | B104: =hybridRentMo+storMo+rentSetup/amort
A105: Cheaper to buy it? | B105: =IF(hybridBuyTotal<=hybridRentTotal,"Yes","No")
A108: 9. THE ROUTES - ONE ROW EACH, EVERY COLUMN A FORMULA
A109: Route | B109: Group | C109: Hardware | D109: Power & rack | E109: People | F109: Tokens, seats, rent | G109: Developer time | H109: Monthly total | I109: Up front | J109: Monthly cash | K109: Full term | L109: Cash, full term | M109: Year-one cash | N109: Per dev / mo | O109: AI $ / task | P109: Unfinished | Q109: Sustained tok/s | R109: Token mult | S109: Session tok/s | T109: Live sessions | U109: Developers held | V109: Headroom | W109: Rank | X109: id
A110: Local model on laptops | B110: Your own hardware | C110: =devs*lapUplift/amort | D110: =devs*lapWatts/1000*codeHrs*workdays*kwhOffice | E110: =IF(labourYN="Yes",devs*lapSupport/12*itRate,0) | F110: =0 | G110: =drag_o | H110: =SUM(C110:G110) | I110: =devs*lapUplift | J110: =D110+E110+F110+G110 | K110: =H110*horizon | L110: =I110+J110*horizon | M110: =I110+J110*MIN(12,horizon) | N110: =IF(devs>0,H110/devs,0) | O110: =IF(acceptedTasks>0,H110/acceptedTasks,0) | P110: =unres_o | Q110: =devs*lapTps | R110: =IF(tm_o>0,tm_o,1) | S110: =sessTps*R110 | T110: =devs | U110: ="scales 1:1" | V110: =IF(S110>0,(lapTps)/S110,0) | W110: =RANK(H110,$H$110:$H$119,1)+COUNTIF($H$110:H110,H110)-1 | X110: laptop
A111: GPUs you buy | B111: Your own hardware | C111: =hwCapex/amort | D111: =fleetKw*pue*730*kwhDc+fleetKw*coloKw+storMo+warrantyMo | E111: =platformMo+adminMo+setupLabour/amort | F111: =0 | G111: =drag_o | H111: =SUM(C111:G111) | I111: =buyUpfront | J111: =D111+E111+F111+G111 | K111: =H111*horizon | L111: =I111+J111*horizon | M111: =I111+J111*MIN(12,horizon) | N111: =IF(devs>0,H111/devs,0) | O111: =IF(acceptedTasks>0,H111/acceptedTasks,0) | P111: =unres_o | Q111: =fleetTps | R111: =IF(tm_o>0,tm_o,1) | S111: =sessTps*R111 | T111: =IF(S111>0,Q111/S111,0) | U111: =IF(sessConc>0,T111/sessConc,0) | V111: =IF(liveSessions*S111>0,Q111/(liveSessions*S111),0) | W111: =RANK(H111,$H$110:$H$119,1)+COUNTIF($H$110:H111,H111)-1 | X111: buy
...

Sheet Catalogues
A1: Catalogues
A2: Specifications and list prices the dropdowns on Inputs read from. Every figure here is a published list price or vendor spec; edit a cell to use your own.
A4: OPEN-WEIGHT MODEL
A5: Open-weight model | B5: Total B | C5: Active B | D5: KV MB/k tok
A6: Qwen3-Coder 480B-A35B | B6: 480 | C6: 35 | D6: 0.25
A7: DeepSeek-V3 671B-A37B | B7: 671 | C7: 37 | D7: 0.07
A8: Kimi K2 1T-A32B | B8: 1000 | C8: 32 | D8: 0.06
A9: GLM 355B-A32B | B9: 355 | C9: 32 | D9: 0.22
A10: Llama 3.1 405B dense | B10: 405 | C10: 405 | D10: 0.52
A11: gpt-oss 120B-A5.1B | B11: 117 | C11: 5.1 | D11: 0.14
A12: Llama 3.3 70B dense | B12: 70 | C12: 70 | D12: 0.31
A13: Qwen3 32B dense | B13: 32 | C13: 32 | D13: 0.26
A14: Devstral 24B dense | B14: 24 | C14: 24 | D14: 0.16
A15: gpt-oss 20B-A3.6B | B15: 21 | C15: 3.6 | D15: 0.09
A16: Active parameters drive decode speed; total parameters drive memory. A mixture-of-experts model holds all of the first and reads only the second.
A18: WEIGHT PRECISION
A19: Weight precision | B19: Bytes/param | C19: KV factor
A20: BF16 / FP16 | B20: 2 | C20: 1
A21: FP8 / INT8 | B21: 1 | C21: 0.5
A22: INT4 / MXFP4 | B22: 0.55 | C22: 0.5
A24: ACCELERATOR
A25: Accelerator | B25: Memory GB | C25: Bandwidth GB/s | D25: Dense TFLOPS | E25: Buy $ | F25: Rent $/h | G25: Draw W
A26: A100 80GB SXM | B26: 80 | C26: 2039 | D26: 312 | E26: 12000 | F26: 1.1 | G26: 400
A27: H100 80GB SXM | B27: 80 | C27: 3350 | D27: 990 | E27: 31000 | F27: 2.4 | G27: 700
A28: H200 141GB SXM | B28: 141 | C28: 4800 | D28: 990 | E28: 34000 | F28: 3.2 | G28: 700
A29: B200 180GB | B29: 180 | C29: 8000 | D29: 2250 | E29: 55000 | F29: 6 | G29: 1000
A30: MI300X 192GB | B30: 192 | C30: 5300 | D30: 1300 | E30: 18000 | F30: 2 | G30: 750
A31: L40S 48GB | B31: 48 | C31: 864 | D31: 362 | E31: 8000 | F31: 1.1 | G31: 350
A32: RTX 6000 Ada 48GB | B32: 48 | C32: 960 | D32: 364 | E32: 7000 | F32: 0.9 | G32: 300
A33: RTX 5090 32GB | B33: 32 | C33: 1792 | D33: 838 | E33: 2500 | F33: 0.7 | G33: 575
A34: Purchase prices are street estimates for whole systems, not quotes.
A36: FLAT PLAN
A37: Flat plan | B37: $/seat/mo | C37: Platform seat $ | D37: Sustained tok/min
A38: GitHub Copilot Pro - individual | B38: 10 | C38: 0 | D38: 300
A39: Claude Pro - individual | B39: 20 | C39: 0 | D39: 350
A40: Cursor Pro - individual | B40: 20 | C40: 0 | D40: 350
A41: ChatGPT Plus - individual | B41: 20 | C41: 0 | D41: 350
A42: Claude Max 5x - individual | B42: 100 | C42: 0 | D42: 1800
A43: Claude Max 20x - individual | B43: 200 | C43: 0 | D43: 7000
A44: ChatGPT Pro - individual | B44: 200 | C44: 0 | D44: 7000
A45: Cursor Standard - team | B45: 40 | C45: 0 | D45: 900
A46: Cursor Premium - team | B46: 120 | C46: 0 | D46: 2200
A47: GitHub Copilot Enterprise | B47: 39 | C47: 21 | D47: 900
A48: Sustained tok/min is an ESTIMATE of what each plan's rate limits allow an agent to pull, not a published figure. Treat it as a starting point and measure your own.
A50: FRONTIER RATE CARD
A51: Frontier rate card | B51: Lab | C51: In $/M | D51: Out $/M | E51: Cache read $/M
A52: Claude Sonnet 5 | B52: Anthropic | C52: 2 | D52: 10 | E52: 0.2
A53: Claude Opus 5 | B53: Anthropic | C53: 15 | D53: 75 | E53: 1.5
A54: Claude Haiku 4.5 | B54: Anthropic | C54: 1 | D54: 5 | E54: 0.1
A55: GPT-5.6 Sol | B55: OpenAI | C55: 4 | D55: 20 | E55: 0.4
A56: List prices move. Check them against the vendor's pricing page before quoting anyone.
A58: EFFECTIVENESS PROFILE
A59: Effectiveness profile | B59: Frontier 1st pass | C59: Open 1st pass | D59: Frontier repair | E59: Open repair | F59: Frontier never | G59: Open never
A60: Observed - mid-range of published results | B60: 0.45 | C60: 0.34 | D60: 0.35 | E60: 0.3 | F60: 0.05 | G60: 0.12
A61: Optimistic - top of SWE-bench Pro | B61: 0.58 | C61: 0.48 | D61: 0.4 | E61: 0.35 | F61: 0.03 | G61: 0.08
A62: Conservative - hard, unfamiliar repos | B62: 0.36 | C62: 0.25 | D62: 0.28 | E62: 0.22 | F62: 0.1 | G62: 0.22
A63: Anchored on SWE-bench Pro pass@1. To depart from a profile, type your own number into the Override column on Inputs - it beats the catalogue wherever it is not blank.
